[
  {
    "id": "2331130",
    "title": "驻南非使馆提醒中国公民加强防范",
    "timestamp": 1765248092,
    "hot": 12080512,
    "url": "https://p11-sign.douyinpic.com/tos-cn-p-0015/oo0bGIeIDyFPxCiyAEfgAUC2SFyenSBBlkO7o3~noop.jpeg?lk3s=bfd515bb&x-expires=1765274400&x-signature=%2FPmwLp7gb3l3wr%2Fxtrp37TG3nk0%3D&from=3218412987",
    "mobileUrl": "https://p11-sign.douyinpic.com/tos-cn-p-0015/oo0bGIeIDyFPxCiyAEfgAUC2SFyenSBBlkO7o3~noop.jpeg?lk3s=bfd515bb&x-expires=1765274400&x-signature=%2FPmwLp7gb3l3wr%2Fxtrp37TG3nk0%3D&from=3218412987"
  },
  {
    "id": "2330052",
    "title": "谁来看下这女生什么球风",
    "timestamp": 1765153601,
    "hot": 11613889,
    "url": "https://p3-sign.douyinpic.com/tos-cn-p-0015/oE89AhfDNEeN9MpAKpyEMMz6zBKADEQNFC5QIg~noop.jpeg?lk3s=bfd515bb&x-expires=1765274400&x-signature=NFt3zGqtQiST2JV46m0XANOrLVA%3D&from=3218412987",
    "mobileUrl": "https://p3-sign.douyinpic.com/tos-cn-p-0015/oE89AhfDNEeN9MpAKpyEMMz6zBKADEQNFC5QIg~noop.jpeg?lk3s=bfd515bb&x-expires=1765274400&x-signature=NFt3zGqtQiST2JV46m0XANOrLVA%3D&from=3218412987"
  },
  {
    "id": "2331097",
    "title": "大国小巷首善之治",
    "timestamp": 1765245794,
    "hot": 11245149,
    "url": "https://p3-sign.douyinpic.com/tos-cn-p-0015/osoOiAAi7Ixxg9BgmXANZeIqQdssBfjBNO1pg2~noop.jpeg?lk3s=bfd515bb&x-expires=1765274400&x-signature=NsbJInhjKr4l6jjuEw87%2BpJ5WE4%3D&from=3218412987",
    "mobileUrl": "https://p3-sign.douyinpic.com/tos-cn-p-0015/osoOiAAi7Ixxg9BgmXANZeIqQdssBfjBNO1pg2~noop.jpeg?lk3s=bfd515bb&x-expires=1765274400&x-signature=NsbJInhjKr4l6jjuEw87%2BpJ5WE4%3D&from=3218412987"
  },
  {
    "id": "2331092",
    "title": "河北沧州杀妻案一审宣判",
    "timestamp": 1765245622,
    "hot": 11109580,
    "url": "https://p3-sign.douyinpic.com/tos-cn-p-0015/oIfAkf4vjgz9D3oQJA6EA6BNBANFQXDKpjPTmR~noop.jpeg?lk3s=bfd515bb&x-expires=1765274400&x-signature=CEdyWWCrR5M94bqK1n%2FyNROM1z0%3D&from=3218412987",
    "mobileUrl": "https://p3-sign.douyinpic.com/tos-cn-p-0015/oIfAkf4vjgz9D3oQJA6EA6BNBANFQXDKpjPTmR~noop.jpeg?lk3s=bfd515bb&x-expires=1765274400&x-signature=CEdyWWCrR5M94bqK1n%2FyNROM1z0%3D&from=3218412987"
  },
  {
    "id": "2330648",
    "title": "麦老师的头好疼",
    "timestamp": 1765185693,
    "hot": 10476379,
    "url": "https://p3-sign.douyinpic.com/tos-cn-p-0015/oAyaDiBieAA0yIzuy2iEULBARBpg4x5Zm0f9wQ~noop.jpeg?lk3s=bfd515bb&x-expires=1765274400&x-signature=cOmoefzn%2BH3pWLpd56DkOBLv39s%3D&from=3218412987",
    "mobileUrl": "https://p3-sign.douyinpic.com/tos-cn-p-0015/oAyaDiBieAA0yIzuy2iEULBARBpg4x5Zm0f9wQ~noop.jpeg?lk3s=bfd515bb&x-expires=1765274400&x-signature=cOmoefzn%2BH3pWLpd56DkOBLv39s%3D&from=3218412987"
  },
  {
    "id": "2330976",
    "title": "日本又发生6.6级地震",
    "timestamp": 1765235779,
    "hot": 10435854,
    "url": "https://p3-sign.douyinpic.com/tos-cn-p-0015/owBgevBVmQ6fsLxl3NYcC6UiBA3iEA0TAIgAi1~noop.jpeg?lk3s=bfd515bb&x-expires=1765274400&x-signature=n6TRy6UdYoXHJwVg6mXHUUi4zA8%3D&from=3218412987",
    "mobileUrl": "https://p3-sign.douyinpic.com/tos-cn-p-0015/owBgevBVmQ6fsLxl3NYcC6UiBA3iEA0TAIgAi1~noop.jpeg?lk3s=bfd515bb&x-expires=1765274400&x-signature=n6TRy6UdYoXHJwVg6mXHUUi4zA8%3D&from=3218412987"
  },
  {
    "id": "2330223",
    "title": "难道不是想要爆米花吗",
    "timestamp": 1765164331,
    "hot": 9215675,
    "url": "https://p26-sign.douyinpic.com/tos-cn-p-0015c000-ce/os4QBeYeILAdyaIgQ7QGQpt8rWXp1KS1BJneDs~noop.jpeg?lk3s=bfd515bb&x-expires=1765274400&x-signature=Balyrz9XaALnCuTdxTUAfjAbKwc%3D&from=3218412987",
    "mobileUrl": "https://p26-sign.douyinpic.com/tos-cn-p-0015c000-ce/os4QBeYeILAdyaIgQ7QGQpt8rWXp1KS1BJneDs~noop.jpeg?lk3s=bfd515bb&x-expires=1765274400&x-signature=Balyrz9XaALnCuTdxTUAfjAbKwc%3D&from=3218412987"
  },
  {
    "id": "2331106",
    "title": "苏炳添宣布退役",
    "timestamp": 1765246371,
    "hot": 9006985,
    "url": "https://p3-sign.douyinpic.com/tos-cn-p-0015/o8gA2EfDgpcBXLEFfkp9ABAiIj3pvNIU4xdACD~noop.jpeg?lk3s=bfd515bb&x-expires=1765274400&x-signature=O6kzZbLYPb7kHknc8TCXPmmcpDk%3D&from=3218412987",
    "mobileUrl": "https://p3-sign.douyinpic.com/tos-cn-p-0015/o8gA2EfDgpcBXLEFfkp9ABAiIj3pvNIU4xdACD~noop.jpeg?lk3s=bfd515bb&x-expires=1765274400&x-signature=O6kzZbLYPb7kHknc8TCXPmmcpDk%3D&from=3218412987"
  },
  {
    "id": "2330873",
    "title": "全国首台“人造太阳”冲刺商业化",
    "timestamp": 1765200768,
    "hot": 8286834,
    "url": "https://p26-sign.douyinpic.com/tos-cn-p-0015/osCcAA0bKLJeLBQOgSIGYfeMgD7QAPbJBEth57~noop.jpeg?lk3s=bfd515bb&x-expires=1765274400&x-signature=cXhJf%2B%2FgKAs2SnKFsMdQ4FqS%2FqU%3D&from=3218412987",
    "mobileUrl": "https://p26-sign.douyinpic.com/tos-cn-p-0015/osCcAA0bKLJeLBQOgSIGYfeMgD7QAPbJBEth57~noop.jpeg?lk3s=bfd515bb&x-expires=1765274400&x-signature=cXhJf%2B%2FgKAs2SnKFsMdQ4FqS%2FqU%3D&from=3218412987"
  },
  {
    "id": "2331187",
    "title": "白天辉被执行死刑",
    "timestamp": 1765251091,
    "hot": 8271295,
    "url": "https://p3-sign.douyinpic.com/tos-cn-p-0015/oYCwAB3ieNyvSWcTlgKe0ImmIA80ByBpx7zAiB~noop.jpeg?lk3s=bfd515bb&x-expires=1765274400&x-signature=ZEbWbONIhmjS209Wu1TzhhU5%2BQU%3D&from=3218412987",
    "mobileUrl": "https://p3-sign.douyinpic.com/tos-cn-p-0015/oYCwAB3ieNyvSWcTlgKe0ImmIA80ByBpx7zAiB~noop.jpeg?lk3s=bfd515bb&x-expires=1765274400&x-signature=ZEbWbONIhmjS209Wu1TzhhU5%2BQU%3D&from=3218412987"
  },
  {
    "id": "2330927",
    "title": "日本发生7.5级地震",
    "timestamp": 1765204001,
    "hot": 8216289,
    "url": "https://p26-sign.douyinpic.com/tos-cn-p-0015/oYTbCfNVDAspFuHAZ2E4uZIZNBNIewXgtw9AGA~noop.jpeg?lk3s=bfd515bb&x-expires=1765274400&x-signature=nmK09cSy%2FIrq25iZGFo%2BS%2B5UEVI%3D&from=3218412987",
    "mobileUrl": "https://p26-sign.douyinpic.com/tos-cn-p-0015/oYTbCfNVDAspFuHAZ2E4uZIZNBNIewXgtw9AGA~noop.jpeg?lk3s=bfd515bb&x-expires=1765274400&x-signature=nmK09cSy%2FIrq25iZGFo%2BS%2B5UEVI%3D&from=3218412987"
  },
  {
    "id": "2331018",
    "title": "J35在鞍山附近坠毁系谣言",
    "timestamp": 1765238786,
    "hot": 8061383,
    "url": "https://p3-sign.douyinpic.com/tos-cn-p-0015/oMyBlLSBIQJQAQbHsuekeF3A7w2eSGGQBGtTCr~noop.jpeg?lk3s=bfd515bb&x-expires=1765274400&x-signature=X3KgXKRKM0o4gNaWe9i0vwiBDoM%3D&from=3218412987",
    "mobileUrl": "https://p3-sign.douyinpic.com/tos-cn-p-0015/oMyBlLSBIQJQAQbHsuekeF3A7w2eSGGQBGtTCr~noop.jpeg?lk3s=bfd515bb&x-expires=1765274400&x-signature=X3KgXKRKM0o4gNaWe9i0vwiBDoM%3D&from=3218412987"
  },
  {
    "id": "2330140",
    "title": "破桶也能敲出演唱会既视感",
    "timestamp": 1765160714,
    "hot": 7998382,
    "url": "https://p3-sign.douyinpic.com/tos-cn-p-0015c000-ce/oUUAuiDBwNNBihEifF0eEEAwI81BimIUqNKcLn~noop.jpeg?lk3s=bfd515bb&x-expires=1765274400&x-signature=xuhiqHHpJw66b0HMAYBomOUu6Is%3D&from=3218412987",
    "mobileUrl": "https://p3-sign.douyinpic.com/tos-cn-p-0015c000-ce/oUUAuiDBwNNBihEifF0eEEAwI81BimIUqNKcLn~noop.jpeg?lk3s=bfd515bb&x-expires=1765274400&x-signature=xuhiqHHpJw66b0HMAYBomOUu6Is%3D&from=3218412987"
  },
  {
    "id": "2330165",
    "title": "双12冬日氛围感穿搭大赏",
    "timestamp": 1765161650,
    "hot": 7853956,
    "url": "https://p11-sign.douyinpic.com/tos-cn-p-0015/ocefSBQ5kJDVAUAiQuxBCL0ryGFY7aoEKr7pfP~noop.jpeg?lk3s=bfd515bb&x-expires=1765274400&x-signature=N4f6Eg81xpG0YTB7uzPe3RzFegI%3D&from=3218412987",
    "mobileUrl": "https://p11-sign.douyinpic.com/tos-cn-p-0015/ocefSBQ5kJDVAUAiQuxBCL0ryGFY7aoEKr7pfP~noop.jpeg?lk3s=bfd515bb&x-expires=1765274400&x-signature=N4f6Eg81xpG0YTB7uzPe3RzFegI%3D&from=3218412987"
  },
  {
    "id": "2330290",
    "title": "年度最爱数码好物盘点",
    "timestamp": 1765167309,
    "hot": 7853509,
    "url": "https://p11-sign.douyinpic.com/tos-cn-p-0015c000-ce/oUD1bnwLIBWNNEEosf9jAZeEv1XxYwvjBKA6Fp~noop.jpeg?lk3s=bfd515bb&x-expires=1765274400&x-signature=FUN4dI1Q5LM0373mxmHY%2FeFgal0%3D&from=3218412987",
    "mobileUrl": "https://p11-sign.douyinpic.com/tos-cn-p-0015c000-ce/oUD1bnwLIBWNNEEosf9jAZeEv1XxYwvjBKA6Fp~noop.jpeg?lk3s=bfd515bb&x-expires=1765274400&x-signature=FUN4dI1Q5LM0373mxmHY%2FeFgal0%3D&from=3218412987"
  },
  {
    "id": "2330319",
    "title": "跟着蛋神煮鸡蛋",
    "timestamp": 1765168367,
    "hot": 7840303,
    "url": "https://p3-sign.douyinpic.com/tos-cn-p-0015/ogEeBigEEh0B7FAtIB0nQNimRmv0TAfiz2A7dA~noop.jpeg?lk3s=bfd515bb&x-expires=1765274400&x-signature=BBhmDamxUdE%2BqdRbUURNRnB8vGU%3D&from=3218412987",
    "mobileUrl": "https://p3-sign.douyinpic.com/tos-cn-p-0015/ogEeBigEEh0B7FAtIB0nQNimRmv0TAfiz2A7dA~noop.jpeg?lk3s=bfd515bb&x-expires=1765274400&x-signature=BBhmDamxUdE%2BqdRbUURNRnB8vGU%3D&from=3218412987"
  },
  {
    "id": "2330960",
    "title": "陈妍希剧宣状态满40减20",
    "timestamp": 1765206037,
    "hot": 7810534,
    "url": "https://p3-sign.douyinpic.com/tos-cn-p-0015c000-ce/oMasaCgJTI2P73IUTMjiZxnZBvJBgKi2AFwAo~noop.jpeg?lk3s=bfd515bb&x-expires=1765274400&x-signature=ksC8GZF03FkNQxtAC1cR2G1RgwA%3D&from=3218412987",
    "mobileUrl": "https://p3-sign.douyinpic.com/tos-cn-p-0015c000-ce/oMasaCgJTI2P73IUTMjiZxnZBvJBgKi2AFwAo~noop.jpeg?lk3s=bfd515bb&x-expires=1765274400&x-signature=ksC8GZF03FkNQxtAC1cR2G1RgwA%3D&from=3218412987"
  },
  {
    "id": "2331007",
    "title": "王毅：台湾地位已被“七重锁定”",
    "timestamp": 1765237962,
    "hot": 7778922,
    "url": "https://p3-sign.douyinpic.com/tos-cn-p-0015/oEEA7A0AKYeDiO2Ai7A0oIIB3gZNmZrBLFfNC2~noop.jpeg?lk3s=bfd515bb&x-expires=1765274400&x-signature=vryCisZ5pSQk4wNEB4EkTmMOj3s%3D&from=3218412987",
    "mobileUrl": "https://p3-sign.douyinpic.com/tos-cn-p-0015/oEEA7A0AKYeDiO2Ai7A0oIIB3gZNmZrBLFfNC2~noop.jpeg?lk3s=bfd515bb&x-expires=1765274400&x-signature=vryCisZ5pSQk4wNEB4EkTmMOj3s%3D&from=3218412987"
  },
  {
    "id": "2330558",
    "title": "狙击蝴蝶抖音追剧团",
    "timestamp": 1765181721,
    "hot": 7755745,
    "url": "https://p11-sign.douyinpic.com/tos-cn-p-0015c000-ce/oQPQAo2Q2Rp3ThkKILbfDZIssGpyeeAe2DGixc~noop.jpeg?lk3s=bfd515bb&x-expires=1765274400&x-signature=dHvEUOoqktx2vbB0leI9IyUQR%2Fk%3D&from=3218412987",
    "mobileUrl": "https://p11-sign.douyinpic.com/tos-cn-p-0015c000-ce/oQPQAo2Q2Rp3ThkKILbfDZIssGpyeeAe2DGixc~noop.jpeg?lk3s=bfd515bb&x-expires=1765274400&x-signature=dHvEUOoqktx2vbB0leI9IyUQR%2Fk%3D&from=3218412987"
  },
  {
    "id": "2330193",
    "title": "东方美学被明制汉服拿捏了",
    "timestamp": 1765163187,
    "hot": 7751813,
    "url": "https://p3-sign.douyinpic.com/tos-cn-i-0813c000-ce/o03wTKNeAOQAD1op92nCEvaCDiIjEAioAAAKfB~noop.jpeg?lk3s=bfd515bb&x-expires=1765274400&x-signature=nAbmhIOVcqUaK9Ss27sHUrQjOgk%3D&from=3218412987",
    "mobileUrl": "https://p3-sign.douyinpic.com/tos-cn-i-0813c000-ce/o03wTKNeAOQAD1op92nCEvaCDiIjEAioAAAKfB~noop.jpeg?lk3s=bfd515bb&x-expires=1765274400&x-signature=nAbmhIOVcqUaK9Ss27sHUrQjOgk%3D&from=3218412987"
  },
  {
    "id": "2330629",
    "title": "卫健委通报护士患癌请假遭拒",
    "timestamp": 1765184901,
    "hot": 7744901,
    "url": "https://p3-sign.douyinpic.com/tos-cn-p-0015/ocaITg2PvQIhA7Awo5ikAwiSXaB9uFPOIvRBT~noop.jpeg?lk3s=bfd515bb&x-expires=1765274400&x-signature=FR56LbigMq02kkyo2ABBE8tg%2F34%3D&from=3218412987",
    "mobileUrl": "https://p3-sign.douyinpic.com/tos-cn-p-0015/ocaITg2PvQIhA7Awo5ikAwiSXaB9uFPOIvRBT~noop.jpeg?lk3s=bfd515bb&x-expires=1765274400&x-signature=FR56LbigMq02kkyo2ABBE8tg%2F34%3D&from=3218412987"
  },
  {
    "id": "2330424",
    "title": "狙击蝴蝶热度破25000",
    "timestamp": 1765174791,
    "hot": 7740908,
    "url": "https://p26-sign.douyinpic.com/tos-cn-i-0813c000-ce/ocevAeqBySkXIgIfJsiLMBJGFYASaQ7raYQAAJ~noop.jpeg?lk3s=bfd515bb&x-expires=1765274400&x-signature=moRCIkddKnNFjSNgeNu82tbS0Mk%3D&from=3218412987",
    "mobileUrl": "https://p26-sign.douyinpic.com/tos-cn-i-0813c000-ce/ocevAeqBySkXIgIfJsiLMBJGFYASaQ7raYQAAJ~noop.jpeg?lk3s=bfd515bb&x-expires=1765274400&x-signature=moRCIkddKnNFjSNgeNu82tbS0Mk%3D&from=3218412987"
  },
  {
    "id": "2330238",
    "title": "留子生存争霸赛开赛啦",
    "timestamp": 1765164687,
    "hot": 7737351,
    "url": "https://p3-sign.douyinpic.com/tos-cn-p-0015c000-ce/o81ZoMiDgxNW9PBAiZNTqkabXAsDJIlPtEPvu~noop.jpeg?lk3s=bfd515bb&x-expires=1765274400&x-signature=Cw99mTF7S3vpVHXqw4%2B9QmQW4NI%3D&from=3218412987",
    "mobileUrl": "https://p3-sign.douyinpic.com/tos-cn-p-0015c000-ce/o81ZoMiDgxNW9PBAiZNTqkabXAsDJIlPtEPvu~noop.jpeg?lk3s=bfd515bb&x-expires=1765274400&x-signature=Cw99mTF7S3vpVHXqw4%2B9QmQW4NI%3D&from=3218412987"
  },
  {
    "id": "2330298",
    "title": "EXO官抖更新了",
    "timestamp": 1765167655,
    "hot": 7731364,
    "url": "https://p3-sign.douyinpic.com/tos-cn-p-0015/oYAC1ia6EmpsBQ3CefsBqiAxgDi0AMlIz0q2IR~noop.jpeg?lk3s=bfd515bb&x-expires=1765274400&x-signature=2mX69xU6MehuPqrIxKLpNhZ69qM%3D&from=3218412987",
    "mobileUrl": "https://p3-sign.douyinpic.com/tos-cn-p-0015/oYAC1ia6EmpsBQ3CefsBqiAxgDi0AMlIz0q2IR~noop.jpeg?lk3s=bfd515bb&x-expires=1765274400&x-signature=2mX69xU6MehuPqrIxKLpNhZ69qM%3D&from=3218412987"
  },
  {
    "id": "2330478",
    "title": "陈小春独家记忆唱哭赛丽亚",
    "timestamp": 1765176908,
    "hot": 7728366,
    "url": "https://p11-sign.douyinpic.com/tos-cn-p-0015c000-ce/o0DEAYibNL5aKBFEISIGMQeYQE8fg9W3JQsrf7~noop.jpeg?lk3s=bfd515bb&x-expires=1765274400&x-signature=xE8orQVP2i7KwFP63yFpd%2FnG7Lk%3D&from=3218412987",
    "mobileUrl": "https://p11-sign.douyinpic.com/tos-cn-p-0015c000-ce/o0DEAYibNL5aKBFEISIGMQeYQE8fg9W3JQsrf7~noop.jpeg?lk3s=bfd515bb&x-expires=1765274400&x-signature=xE8orQVP2i7KwFP63yFpd%2FnG7Lk%3D&from=3218412987"
  },
  {
    "id": "2330616",
    "title": "俄罗斯盗版疯狂动物城上映",
    "timestamp": 1765184454,
    "hot": 7724673,
    "url": "https://p11-sign.douyinpic.com/tos-cn-p-0015c000-ce/o46sIM6k7itkCOoXHga5vy2K4SPAAiVEs9hBA~noop.jpeg?lk3s=bfd515bb&x-expires=1765274400&x-signature=05cRe1C1YbGwFLpWwrIu80kXbnQ%3D&from=3218412987",
    "mobileUrl": "https://p11-sign.douyinpic.com/tos-cn-p-0015c000-ce/o46sIM6k7itkCOoXHga5vy2K4SPAAiVEs9hBA~noop.jpeg?lk3s=bfd515bb&x-expires=1765274400&x-signature=05cRe1C1YbGwFLpWwrIu80kXbnQ%3D&from=3218412987"
  },
  {
    "id": "2330531",
    "title": "朱孝天回应缺席F4演唱会",
    "timestamp": 1765180412,
    "hot": 7723456,
    "url": "https://p3-sign.douyinpic.com/tos-cn-p-0015/ocBQAHHqEFAUqNGgQ9EDNcD9nXfo92pscAUfB2~noop.jpeg?lk3s=bfd515bb&x-expires=1765274400&x-signature=w30QPqC59Ks1wfAHC%2FTwwscoZDU%3D&from=3218412987",
    "mobileUrl": "https://p3-sign.douyinpic.com/tos-cn-p-0015/ocBQAHHqEFAUqNGgQ9EDNcD9nXfo92pscAUfB2~noop.jpeg?lk3s=bfd515bb&x-expires=1765274400&x-signature=w30QPqC59Ks1wfAHC%2FTwwscoZDU%3D&from=3218412987"
  },
  {
    "id": "2330222",
    "title": "用一条日常拥抱冬天",
    "timestamp": 1765164327,
    "hot": 7719025,
    "url": "https://p3-sign.douyinpic.com/tos-cn-p-0015c000-ce/ooUye07gmspiAhmOEAIYCzKfhohwniEBAroBZU~noop.jpeg?lk3s=bfd515bb&x-expires=1765274400&x-signature=J%2FnRG9cmxrdOKLgqJwyj5p1GtYA%3D&from=3218412987",
    "mobileUrl": "https://p3-sign.douyinpic.com/tos-cn-p-0015c000-ce/ooUye07gmspiAhmOEAIYCzKfhohwniEBAroBZU~noop.jpeg?lk3s=bfd515bb&x-expires=1765274400&x-signature=J%2FnRG9cmxrdOKLgqJwyj5p1GtYA%3D&from=3218412987"
  },
  {
    "id": "2330712",
    "title": "野外探险中的头号杀手",
    "timestamp": 1765189426,
    "hot": 7716497,
    "url": "https://p3-sign.douyinpic.com/tos-cn-i-0813c000-ce/o0c9fABl8PAEIiep0h3C5AnAwEcsCZVIAA9hi4~noop.jpeg?lk3s=bfd515bb&x-expires=1765274400&x-signature=%2BCtZluuvSRbj7FhFPYLMO9mkTkE%3D&from=3218412987",
    "mobileUrl": "https://p3-sign.douyinpic.com/tos-cn-i-0813c000-ce/o0c9fABl8PAEIiep0h3C5AnAwEcsCZVIAA9hi4~noop.jpeg?lk3s=bfd515bb&x-expires=1765274400&x-signature=%2BCtZluuvSRbj7FhFPYLMO9mkTkE%3D&from=3218412987"
  },
  {
    "id": "2331161",
    "title": "风与潮开播",
    "timestamp": 1765249736,
    "hot": 7712481,
    "url": "https://p11-sign.douyinpic.com/tos-cn-p-0015c000-ce/o8CkAijN1F85eA4FIpEDpvfXI6FCwpdaEe3bq9~noop.jpeg?lk3s=bfd515bb&x-expires=1765274400&x-signature=jDjDdp7pNhWtrx%2BWuvr0IrzfJm8%3D&from=3218412987",
    "mobileUrl": "https://p11-sign.douyinpic.com/tos-cn-p-0015c000-ce/o8CkAijN1F85eA4FIpEDpvfXI6FCwpdaEe3bq9~noop.jpeg?lk3s=bfd515bb&x-expires=1765274400&x-signature=jDjDdp7pNhWtrx%2BWuvr0IrzfJm8%3D&from=3218412987"
  },
  {
    "id": "2331160",
    "title": "杨超越董思成我会站在你身后",
    "timestamp": 1765249721,
    "hot": 7699306,
    "url": "https://p26-sign.douyinpic.com/tos-cn-p-0015/oMg80AI8GDBagWAxIbUABOQ3ODi8emNijN3Yfj~noop.jpeg?lk3s=bfd515bb&x-expires=1765274400&x-signature=hmF4M1%2BJcSAIhpYhY7m4EO6xksE%3D&from=3218412987",
    "mobileUrl": "https://p26-sign.douyinpic.com/tos-cn-p-0015/oMg80AI8GDBagWAxIbUABOQ3ODi8emNijN3Yfj~noop.jpeg?lk3s=bfd515bb&x-expires=1765274400&x-signature=hmF4M1%2BJcSAIhpYhY7m4EO6xksE%3D&from=3218412987"
  },
  {
    "id": "2330866",
    "title": "比李雾更先爱上岑矜的是观众",
    "timestamp": 1765200632,
    "hot": 7696675,
    "url": "https://p26-sign.douyinpic.com/tos-cn-p-0015/o4RSiByemARUE704AILHbnEGJeVpflTIBBCc2I~noop.jpeg?lk3s=bfd515bb&x-expires=1765274400&x-signature=AJNV8VoCFK8SsFrhaTAhdXJ1Vl4%3D&from=3218412987",
    "mobileUrl": "https://p26-sign.douyinpic.com/tos-cn-p-0015/o4RSiByemARUE704AILHbnEGJeVpflTIBBCc2I~noop.jpeg?lk3s=bfd515bb&x-expires=1765274400&x-signature=AJNV8VoCFK8SsFrhaTAhdXJ1Vl4%3D&from=3218412987"
  },
  {
    "id": "2330214",
    "title": "打开窗户让孤单透气",
    "timestamp": 1765164024,
    "hot": 7693833,
    "url": "https://p3-sign.douyinpic.com/tos-cn-i-0813c001/oYe8QYC9AAgwuBDrAAgF8IlGIfHupsECBA8zGA~noop.jpeg?lk3s=bfd515bb&x-expires=1765274400&x-signature=5rqoZrdowO%2BnbVITNOUss1rsHC8%3D&from=3218412987",
    "mobileUrl": "https://p3-sign.douyinpic.com/tos-cn-i-0813c001/oYe8QYC9AAgwuBDrAAgF8IlGIfHupsECBA8zGA~noop.jpeg?lk3s=bfd515bb&x-expires=1765274400&x-signature=5rqoZrdowO%2BnbVITNOUss1rsHC8%3D&from=3218412987"
  },
  {
    "id": "2330827",
    "title": "我叫李飞拍打式舞蹈挑战",
    "timestamp": 1765197843,
    "hot": 7686611,
    "url": "https://p3-sign.douyinpic.com/tos-cn-p-0015/oY0NCILIDSEipBmggEfbApCTDFVmHpAAcfH9h2~noop.jpeg?lk3s=bfd515bb&x-expires=1765274400&x-signature=7pk64cmMK9IaLSgN03a4X%2FufxYw%3D&from=3218412987",
    "mobileUrl": "https://p3-sign.douyinpic.com/tos-cn-p-0015/oY0NCILIDSEipBmggEfbApCTDFVmHpAAcfH9h2~noop.jpeg?lk3s=bfd515bb&x-expires=1765274400&x-signature=7pk64cmMK9IaLSgN03a4X%2FufxYw%3D&from=3218412987"
  },
  {
    "id": "2330464",
    "title": "即刻上场晨家立业真亲了",
    "timestamp": 1765176502,
    "hot": 7685675,
    "url": "https://p3-sign.douyinpic.com/tos-cn-p-0015/o4QHPhZWwBUgaAO5o9Q1vTIEiATiaIs6QIW8C~noop.jpeg?lk3s=bfd515bb&x-expires=1765274400&x-signature=JC%2B7kTPQVnvk3MNEWFgCnNHE9Rg%3D&from=3218412987",
    "mobileUrl": "https://p3-sign.douyinpic.com/tos-cn-p-0015/o4QHPhZWwBUgaAO5o9Q1vTIEiATiaIs6QIW8C~noop.jpeg?lk3s=bfd515bb&x-expires=1765274400&x-signature=JC%2B7kTPQVnvk3MNEWFgCnNHE9Rg%3D&from=3218412987"
  },
  {
    "id": "2330995",
    "title": "特朗普警告日本",
    "timestamp": 1765237204,
    "hot": 7684357,
    "url": "https://p3-sign.douyinpic.com/tos-cn-p-0015/oQtAVMpI2ukDlBCwg1C3sfEEFAA98LNeQ9ZMCI~noop.jpeg?lk3s=bfd515bb&x-expires=1765274400&x-signature=dYzLn7Ctmp3Y7uIxLlCWpyzsY1g%3D&from=3218412987",
    "mobileUrl": "https://p3-sign.douyinpic.com/tos-cn-p-0015/oQtAVMpI2ukDlBCwg1C3sfEEFAA98LNeQ9ZMCI~noop.jpeg?lk3s=bfd515bb&x-expires=1765274400&x-signature=dYzLn7Ctmp3Y7uIxLlCWpyzsY1g%3D&from=3218412987"
  },
  {
    "id": "2330314",
    "title": "杨幂 于和伟我罩的",
    "timestamp": 1765168102,
    "hot": 7676321,
    "url": "https://p11-sign.douyinpic.com/tos-cn-p-0015/ooaGweMZI5eTgVLASB9AVoKewEw7C3BbsgBsG3~noop.jpeg?lk3s=bfd515bb&x-expires=1765274400&x-signature=GgC5yODOvbTT195tFWEDa%2FXtGog%3D&from=3218412987",
    "mobileUrl": "https://p11-sign.douyinpic.com/tos-cn-p-0015/ooaGweMZI5eTgVLASB9AVoKewEw7C3BbsgBsG3~noop.jpeg?lk3s=bfd515bb&x-expires=1765274400&x-signature=GgC5yODOvbTT195tFWEDa%2FXtGog%3D&from=3218412987"
  },
  {
    "id": "2330229",
    "title": "电影得闲谨制细节越品越心疼",
    "timestamp": 1765164493,
    "hot": 7668228,
    "url": "https://p3-sign.douyinpic.com/tos-cn-p-0015/oYfizWpDNBAFDEUQGQuE4ZAewvZg1plLDA9qER~noop.jpeg?lk3s=bfd515bb&x-expires=1765274400&x-signature=BeAfqpt5vRa55k9HyV%2FHwkPLVmE%3D&from=3218412987",
    "mobileUrl": "https://p3-sign.douyinpic.com/tos-cn-p-0015/oYfizWpDNBAFDEUQGQuE4ZAewvZg1plLDA9qER~noop.jpeg?lk3s=bfd515bb&x-expires=1765274400&x-signature=BeAfqpt5vRa55k9HyV%2FHwkPLVmE%3D&from=3218412987"
  },
  {
    "id": "2330474",
    "title": "小手不会给你反应的速度",
    "timestamp": 1765176854,
    "hot": 7666713,
    "url": "https://p11-sign.douyinpic.com/tos-cn-p-0015/o8MT2I9RatYKYsQs0sAAgosMPBIyiPAIBDyiI~noop.jpeg?lk3s=bfd515bb&x-expires=1765274400&x-signature=hptY%2B%2FpKZqEOoq%2Binxw2bFDylPc%3D&from=3218412987",
    "mobileUrl": "https://p11-sign.douyinpic.com/tos-cn-p-0015/o8MT2I9RatYKYsQs0sAAgosMPBIyiPAIBDyiI~noop.jpeg?lk3s=bfd515bb&x-expires=1765274400&x-signature=hptY%2B%2FpKZqEOoq%2Binxw2bFDylPc%3D&from=3218412987"
  },
  {
    "id": "2330315",
    "title": "成龙回应“龙叔老了”",
    "timestamp": 1765168104,
    "hot": 7662238,
    "url": "https://p3-sign.douyinpic.com/tos-cn-p-0015/oI9wqAR1AniI2FKpJUCFEiXNIBafTdx18gDSAf~noop.jpeg?lk3s=bfd515bb&x-expires=1765274400&x-signature=R5BQkFgVUwvAhEFTdNLeH9PhxxY%3D&from=3218412987",
    "mobileUrl": "https://p3-sign.douyinpic.com/tos-cn-p-0015/oI9wqAR1AniI2FKpJUCFEiXNIBafTdx18gDSAf~noop.jpeg?lk3s=bfd515bb&x-expires=1765274400&x-signature=R5BQkFgVUwvAhEFTdNLeH9PhxxY%3D&from=3218412987"
  },
  {
    "id": "2330199",
    "title": "萌宠的生活很快活",
    "timestamp": 1765163448,
    "hot": 7657974,
    "url": "https://p3-sign.douyinpic.com/tos-cn-i-0813/oYBTAi3AnIcmMisAzDlfA0b5T1AzCeg7x0ELAA~noop.jpeg?lk3s=bfd515bb&x-expires=1765274400&x-signature=K81Wp1HSrkn7vC6ddn2F17PXIrA%3D&from=3218412987",
    "mobileUrl": "https://p3-sign.douyinpic.com/tos-cn-i-0813/oYBTAi3AnIcmMisAzDlfA0b5T1AzCeg7x0ELAA~noop.jpeg?lk3s=bfd515bb&x-expires=1765274400&x-signature=K81Wp1HSrkn7vC6ddn2F17PXIrA%3D&from=3218412987"
  },
  {
    "id": "2330564",
    "title": "吴克群号召网友共跳希望之舞",
    "timestamp": 1765181973,
    "hot": 7651813,
    "url": "https://p3-sign.douyinpic.com/tos-cn-p-0015/oM9Pipbmgi1eAE800iI4baijACA2DyfUBDBpBr~noop.jpeg?lk3s=bfd515bb&x-expires=1765274400&x-signature=E6rKy5Ed6VPStCz%2F2Rgimq4pZjo%3D&from=3218412987",
    "mobileUrl": "https://p3-sign.douyinpic.com/tos-cn-p-0015/oM9Pipbmgi1eAE800iI4baijACA2DyfUBDBpBr~noop.jpeg?lk3s=bfd515bb&x-expires=1765274400&x-signature=E6rKy5Ed6VPStCz%2F2Rgimq4pZjo%3D&from=3218412987"
  },
  {
    "id": "2330892",
    "title": "章昊BB的合拍十年之内没人能懂",
    "timestamp": 1765201834,
    "hot": 7650804,
    "url": "https://p3-sign.douyinpic.com/tos-cn-p-0015/oMwvtBAZi2BIPIQgbGQRbi02vGdTxiIaAbgMo~noop.jpeg?lk3s=bfd515bb&x-expires=1765274400&x-signature=F9xW4n%2FvJetLuJ1phhL%2BCR2RIAc%3D&from=3218412987",
    "mobileUrl": "https://p3-sign.douyinpic.com/tos-cn-p-0015/oMwvtBAZi2BIPIQgbGQRbi02vGdTxiIaAbgMo~noop.jpeg?lk3s=bfd515bb&x-expires=1765274400&x-signature=F9xW4n%2FvJetLuJ1phhL%2BCR2RIAc%3D&from=3218412987"
  },
  {
    "id": "2329980",
    "title": "泰柬边境再发冲突",
    "timestamp": 1765149521,
    "hot": 7650238,
    "url": "https://p11-sign.douyinpic.com/tos-cn-p-0015/oUoB96GULfODar1Ge7pYAC1BocAggGTeAS18EI~noop.jpeg?lk3s=bfd515bb&x-expires=1765274400&x-signature=AL9qzOd%2BRNmgXKEpX3uV6F8x9ZU%3D&from=3218412987",
    "mobileUrl": "https://p11-sign.douyinpic.com/tos-cn-p-0015/oUoB96GULfODar1Ge7pYAC1BocAggGTeAS18EI~noop.jpeg?lk3s=bfd515bb&x-expires=1765274400&x-signature=AL9qzOd%2BRNmgXKEpX3uV6F8x9ZU%3D&from=3218412987"
  },
  {
    "id": "2330168",
    "title": "冬天就爱这一口土味",
    "timestamp": 1765161755,
    "hot": 7649529,
    "url": "https://p3-sign.douyinpic.com/tos-cn-p-0015c000-ce/oED3xaiPyaS8EYAYCxFMAnZXsFTLIucCiBnvP~noop.jpeg?lk3s=bfd515bb&x-expires=1765274400&x-signature=rL0brpOMj5Sh9wYx5ZIvf0wLotI%3D&from=3218412987",
    "mobileUrl": "https://p3-sign.douyinpic.com/tos-cn-p-0015c000-ce/oED3xaiPyaS8EYAYCxFMAnZXsFTLIucCiBnvP~noop.jpeg?lk3s=bfd515bb&x-expires=1765274400&x-signature=rL0brpOMj5Sh9wYx5ZIvf0wLotI%3D&from=3218412987"
  },
  {
    "id": "2330160",
    "title": "校园歌手大赛有多纯爱",
    "timestamp": 1765161353,
    "hot": 7640745,
    "url": "https://p3-sign.douyinpic.com/tos-cn-p-0015c000-ce/oY8ayZfg1GTWGieICQCpeVAezWFAxkCzMD2qQR~noop.jpeg?lk3s=bfd515bb&x-expires=1765274400&x-signature=llcjD4yRC2W%2BmuK0x6ghQ9ySwSs%3D&from=3218412987",
    "mobileUrl": "https://p3-sign.douyinpic.com/tos-cn-p-0015c000-ce/oY8ayZfg1GTWGieICQCpeVAezWFAxkCzMD2qQR~noop.jpeg?lk3s=bfd515bb&x-expires=1765274400&x-signature=llcjD4yRC2W%2BmuK0x6ghQ9ySwSs%3D&from=3218412987"
  },
  {
    "id": "2330384",
    "title": "2025星光大赏阵容名单",
    "timestamp": 1765172963,
    "hot": 7639967,
    "url": "https://p3-sign.douyinpic.com/tos-cn-p-0015/oUmBX7MhBXAvAfCbxWQGENBfBuJP87VZSsfjAm~noop.jpeg?lk3s=bfd515bb&x-expires=1765274400&x-signature=2lqS8JO0%2F0NFfKOC5nlQ0D%2Ffc30%3D&from=3218412987",
    "mobileUrl": "https://p3-sign.douyinpic.com/tos-cn-p-0015/oUmBX7MhBXAvAfCbxWQGENBfBuJP87VZSsfjAm~noop.jpeg?lk3s=bfd515bb&x-expires=1765274400&x-signature=2lqS8JO0%2F0NFfKOC5nlQ0D%2Ffc30%3D&from=3218412987"
  },
  {
    "id": "2330216",
    "title": "百大美妆课代表年度总结来了",
    "timestamp": 1765164074,
    "hot": 7636373,
    "url": "https://p11-sign.douyinpic.com/tos-cn-p-0015c000-ce/oIyBJaf8eQA0nP16uLT6rfHJigEilCDhSIK7rF~noop.jpeg?lk3s=bfd515bb&x-expires=1765274400&x-signature=UMkksgFIvBOPtoYfSYxzupTQj%2F4%3D&from=3218412987",
    "mobileUrl": "https://p11-sign.douyinpic.com/tos-cn-p-0015c000-ce/oIyBJaf8eQA0nP16uLT6rfHJigEilCDhSIK7rF~noop.jpeg?lk3s=bfd515bb&x-expires=1765274400&x-signature=UMkksgFIvBOPtoYfSYxzupTQj%2F4%3D&from=3218412987"
  },
  {
    "id": "2330618",
    "title": "周深怜悯谁唱谁破碎",
    "timestamp": 1765184496,
    "hot": 7634598,
    "url": "https://p3-sign.douyinpic.com/tos-cn-p-0015c000-ce/os9EUw0SCWe4i8AAiiAgNEIB0wunm0aBoNfOW7~noop.jpeg?lk3s=bfd515bb&x-expires=1765274400&x-signature=e1J2k9SinYTGhIwD4GLoSqbp%2BTI%3D&from=3218412987",
    "mobileUrl": "https://p3-sign.douyinpic.com/tos-cn-p-0015c000-ce/os9EUw0SCWe4i8AAiiAgNEIB0wunm0aBoNfOW7~noop.jpeg?lk3s=bfd515bb&x-expires=1765274400&x-signature=e1J2k9SinYTGhIwD4GLoSqbp%2BTI%3D&from=3218412987"
  }
]