[
  {
    "id": "2529120",
    "title": "美加墨世界杯倒计时1天",
    "timestamp": 1781051353,
    "hot": 12099339,
    "url": "https://p3-sign.douyinpic.com/tos-cn-p-0015/oM1PI7BqAg3IXM9fEEMYfDJAoquDKF31KDUrNA~noop.jpeg?lk3s=bfd515bb&x-expires=1781092800&x-signature=ufcrwAjoHv335RpMU%2FivPpNsbNA%3D&from=3218412987",
    "mobileUrl": "https://p3-sign.douyinpic.com/tos-cn-p-0015/oM1PI7BqAg3IXM9fEEMYfDJAoquDKF31KDUrNA~noop.jpeg?lk3s=bfd515bb&x-expires=1781092800&x-signature=ufcrwAjoHv335RpMU%2FivPpNsbNA%3D&from=3218412987"
  },
  {
    "id": "2529289",
    "title": "解锁粽子新形态",
    "timestamp": 1781060537,
    "hot": 12079038,
    "url": "https://p11-sign.douyinpic.com/tos-cn-p-0015/oki80DEIIAgqIPFfGPFDVMYLXUumXAAyDBT9He~noop.jpeg?lk3s=bfd515bb&x-expires=1781092800&x-signature=My8NTkyfEgABNJYm8ecw2WKyFME%3D&from=3218412987",
    "mobileUrl": "https://p11-sign.douyinpic.com/tos-cn-p-0015/oki80DEIIAgqIPFfGPFDVMYLXUumXAAyDBT9He~noop.jpeg?lk3s=bfd515bb&x-expires=1781092800&x-signature=My8NTkyfEgABNJYm8ecw2WKyFME%3D&from=3218412987"
  },
  {
    "id": "2529259",
    "title": "数看我国经济运行稳中向好",
    "timestamp": 1781059585,
    "hot": 11565179,
    "url": "https://p26-sign.douyinpic.com/tos-cn-p-0015/okelFB0VGghO0QwTAbLdEu7DQCeKUXBgIeAiBU~noop.jpeg?lk3s=bfd515bb&x-expires=1781092800&x-signature=XV7%2BpKi7YDxTJynVg%2F8fG%2Ffe5mw%3D&from=3218412987",
    "mobileUrl": "https://p26-sign.douyinpic.com/tos-cn-p-0015/okelFB0VGghO0QwTAbLdEu7DQCeKUXBgIeAiBU~noop.jpeg?lk3s=bfd515bb&x-expires=1781092800&x-signature=XV7%2BpKi7YDxTJynVg%2F8fG%2Ffe5mw%3D&from=3218412987"
  },
  {
    "id": "2528216",
    "title": "我来写高考作文",
    "timestamp": 1780975082,
    "hot": 11472755,
    "url": "https://p26-sign.douyinpic.com/tos-cn-p-0015/o8o7pSEpn0BzWJGeBgfa3WAIDfAIFBN1MCGUdQ~noop.jpeg?lk3s=bfd515bb&x-expires=1781092800&x-signature=Ki8xA%2B%2Bql2U%2BsyguCfZbUnODjKk%3D&from=3218412987",
    "mobileUrl": "https://p26-sign.douyinpic.com/tos-cn-p-0015/o8o7pSEpn0BzWJGeBgfa3WAIDfAIFBN1MCGUdQ~noop.jpeg?lk3s=bfd515bb&x-expires=1781092800&x-signature=Ki8xA%2B%2Bql2U%2BsyguCfZbUnODjKk%3D&from=3218412987"
  },
  {
    "id": "2528746",
    "title": "用AI复原孔子与苏格拉底教育之辩",
    "timestamp": 1781000549,
    "hot": 10577483,
    "url": "https://p11-sign.douyinpic.com/tos-cn-p-0015/oggUTUXBpCZweA7e10gAiWQBOMMdaSaeh88tDa~noop.jpeg?lk3s=bfd515bb&x-expires=1781092800&x-signature=5Hua3%2FooyCb16wbqGs73RE56GdE%3D&from=3218412987",
    "mobileUrl": "https://p11-sign.douyinpic.com/tos-cn-p-0015/oggUTUXBpCZweA7e10gAiWQBOMMdaSaeh88tDa~noop.jpeg?lk3s=bfd515bb&x-expires=1781092800&x-signature=5Hua3%2FooyCb16wbqGs73RE56GdE%3D&from=3218412987"
  },
  {
    "id": "2528292",
    "title": "又学到了一款粽子的新包法",
    "timestamp": 1780978181,
    "hot": 10428467,
    "url": "https://p3-sign.douyinpic.com/tos-cn-p-0015/owE95sIlf8zhx1DxBgfkFOACDOIM5IBHAWJqYA~noop.jpeg?lk3s=bfd515bb&x-expires=1781092800&x-signature=RPTJu3lSwmBUlcjqRPR%2BYgYc7EQ%3D&from=3218412987",
    "mobileUrl": "https://p3-sign.douyinpic.com/tos-cn-p-0015/owE95sIlf8zhx1DxBgfkFOACDOIM5IBHAWJqYA~noop.jpeg?lk3s=bfd515bb&x-expires=1781092800&x-signature=RPTJu3lSwmBUlcjqRPR%2BYgYc7EQ%3D&from=3218412987"
  },
  {
    "id": "2528205",
    "title": "用运动迎接夏天",
    "timestamp": 1780974631,
    "hot": 9262628,
    "url": "https://p26-sign.douyinpic.com/tos-cn-p-0015/oo9NbVAsvBE8E6PUmmiaoaVqiwinAcBQIu0EI~noop.jpeg?lk3s=bfd515bb&x-expires=1781092800&x-signature=%2Bqz%2FSmnrhudceYcFef10VFdZLBE%3D&from=3218412987",
    "mobileUrl": "https://p26-sign.douyinpic.com/tos-cn-p-0015/oo9NbVAsvBE8E6PUmmiaoaVqiwinAcBQIu0EI~noop.jpeg?lk3s=bfd515bb&x-expires=1781092800&x-signature=%2Bqz%2FSmnrhudceYcFef10VFdZLBE%3D&from=3218412987"
  },
  {
    "id": "2528770",
    "title": "按摩店是年轻人的gap落地签",
    "timestamp": 1781002085,
    "hot": 9258383,
    "url": "https://p11-sign.douyinpic.com/tos-cn-p-0015c000-ce/o0fry8ieJCEF6K2IIIfm3RAG5RmwiqOuDA9nEk~noop.jpeg?lk3s=bfd515bb&x-expires=1781092800&x-signature=Wp8H8abpCV%2B9SMf2xSH%2BXnYEIc4%3D&from=3218412987",
    "mobileUrl": "https://p11-sign.douyinpic.com/tos-cn-p-0015c000-ce/o0fry8ieJCEF6K2IIIfm3RAG5RmwiqOuDA9nEk~noop.jpeg?lk3s=bfd515bb&x-expires=1781092800&x-signature=Wp8H8abpCV%2B9SMf2xSH%2BXnYEIc4%3D&from=3218412987"
  },
  {
    "id": "2528995",
    "title": "西瓜原来可以当成豆腐切",
    "timestamp": 1781013702,
    "hot": 9202775,
    "url": "https://p26-sign.douyinpic.com/tos-cn-p-0015/ogNyEAAF7ICeE9EgVBAJEQIQbDBCDfNBC75qTl~noop.jpeg?lk3s=bfd515bb&x-expires=1781092800&x-signature=JFKgOF5yaYrde3848i4XtrEi1Os%3D&from=3218412987",
    "mobileUrl": "https://p26-sign.douyinpic.com/tos-cn-p-0015/ogNyEAAF7ICeE9EgVBAJEQIQbDBCDfNBC75qTl~noop.jpeg?lk3s=bfd515bb&x-expires=1781092800&x-signature=JFKgOF5yaYrde3848i4XtrEi1Os%3D&from=3218412987"
  },
  {
    "id": "2529144",
    "title": "伊朗袭击美军第五舰队",
    "timestamp": 1781053548,
    "hot": 9175954,
    "url": "https://p5-ex-gddgtc-sign.douyinpic.com/tos-cn-p-0015/oYqBAeWReAL7Ge5QDlRIArCGbBULQ090Un5DPp~noop.jpeg?lk3s=bfd515bb&x-expires=1781092800&x-signature=H%2BKDGAnj%2F2BQMAbY%2BVJKrfiOa0c%3D&from=3218412987",
    "mobileUrl": "https://p5-ex-gddgtc-sign.douyinpic.com/tos-cn-p-0015/oYqBAeWReAL7Ge5QDlRIArCGbBULQ090Un5DPp~noop.jpeg?lk3s=bfd515bb&x-expires=1781092800&x-signature=H%2BKDGAnj%2F2BQMAbY%2BVJKrfiOa0c%3D&from=3218412987"
  },
  {
    "id": "2529251",
    "title": "李沂泽虚报年龄被罚限制参赛3年",
    "timestamp": 1781059025,
    "hot": 9123548,
    "url": "https://p3-sign.douyinpic.com/tos-cn-p-0015/oIwAlBCDqB0eNuQFEFUNPAEZAAUofKzgM9IC8H~noop.jpeg?lk3s=bfd515bb&x-expires=1781092800&x-signature=6n96IA%2BmSjTgDSoRH4DRMJCPZMI%3D&from=3218412987",
    "mobileUrl": "https://p3-sign.douyinpic.com/tos-cn-p-0015/oIwAlBCDqB0eNuQFEFUNPAEZAAUofKzgM9IC8H~noop.jpeg?lk3s=bfd515bb&x-expires=1781092800&x-signature=6n96IA%2BmSjTgDSoRH4DRMJCPZMI%3D&from=3218412987"
  },
  {
    "id": "2528765",
    "title": "美加墨世界杯十大巨星盘点",
    "timestamp": 1781001809,
    "hot": 9057121,
    "url": "https://p3-sign.douyinpic.com/tos-cn-p-0015/oQVO6qRKEyF3AFrBNDCQ6gAfNvkJBADyAQxf9M~noop.jpeg?lk3s=bfd515bb&x-expires=1781092800&x-signature=HNg%2B4AowF6OvBPkBVujYmyu9IAM%3D&from=3218412987",
    "mobileUrl": "https://p3-sign.douyinpic.com/tos-cn-p-0015/oQVO6qRKEyF3AFrBNDCQ6gAfNvkJBADyAQxf9M~noop.jpeg?lk3s=bfd515bb&x-expires=1781092800&x-signature=HNg%2B4AowF6OvBPkBVujYmyu9IAM%3D&from=3218412987"
  },
  {
    "id": "2528658",
    "title": "世界杯预言家已就位",
    "timestamp": 1780995903,
    "hot": 8997326,
    "url": "https://p11-sign.douyinpic.com/tos-cn-p-0015/oMNDlPYnE4yBIwFgqmLAIo6fJDe9BbAJnIAEFR~noop.jpeg?lk3s=bfd515bb&x-expires=1781092800&x-signature=Qvptfk8LwwCayjDMCjrIIIvxbjE%3D&from=3218412987",
    "mobileUrl": "https://p11-sign.douyinpic.com/tos-cn-p-0015/oMNDlPYnE4yBIwFgqmLAIo6fJDe9BbAJnIAEFR~noop.jpeg?lk3s=bfd515bb&x-expires=1781092800&x-signature=Qvptfk8LwwCayjDMCjrIIIvxbjE%3D&from=3218412987"
  },
  {
    "id": "2528854",
    "title": "杭州临安区要热上50℃系谣言",
    "timestamp": 1781006620,
    "hot": 8980043,
    "url": "https://p3-sign.douyinpic.com/tos-cn-p-0015/osgM2Rk6oQ0UDRCtiEmuehJgQfYGeHAaPA4ITe~noop.jpeg?lk3s=bfd515bb&x-expires=1781092800&x-signature=DNfrENeNuZtgqD2KD6%2F950m4pyM%3D&from=3218412987",
    "mobileUrl": "https://p3-sign.douyinpic.com/tos-cn-p-0015/osgM2Rk6oQ0UDRCtiEmuehJgQfYGeHAaPA4ITe~noop.jpeg?lk3s=bfd515bb&x-expires=1781092800&x-signature=DNfrENeNuZtgqD2KD6%2F950m4pyM%3D&from=3218412987"
  },
  {
    "id": "2529220",
    "title": "金价连续大跌",
    "timestamp": 1781057889,
    "hot": 8854200,
    "url": "https://p26-sign.douyinpic.com/tos-cn-p-0015/oQUKDfqgAExCQkiqQDqgFBMRQO9MAYymZAmNPe~noop.jpeg?lk3s=bfd515bb&x-expires=1781092800&x-signature=7uRVhf2WPTVg1YtJUShe47YofZU%3D&from=3218412987",
    "mobileUrl": "https://p26-sign.douyinpic.com/tos-cn-p-0015/oQUKDfqgAExCQkiqQDqgFBMRQO9MAYymZAmNPe~noop.jpeg?lk3s=bfd515bb&x-expires=1781092800&x-signature=7uRVhf2WPTVg1YtJUShe47YofZU%3D&from=3218412987"
  },
  {
    "id": "2529399",
    "title": "耀眼大结局",
    "timestamp": 1781066654,
    "hot": 8667639,
    "url": "https://p3-sign.douyinpic.com/tos-cn-p-0015/oMY3i4qFg98eAIWr1PIggYipANAoDAfHBcCbBx~noop.jpeg?lk3s=bfd515bb&x-expires=1781092800&x-signature=B7rgy7lfxZV1RkaivKhRU6lrmfw%3D&from=3218412987",
    "mobileUrl": "https://p3-sign.douyinpic.com/tos-cn-p-0015/oMY3i4qFg98eAIWr1PIggYipANAoDAfHBcCbBx~noop.jpeg?lk3s=bfd515bb&x-expires=1781092800&x-signature=B7rgy7lfxZV1RkaivKhRU6lrmfw%3D&from=3218412987"
  },
  {
    "id": "2529115",
    "title": "西游记老鼠精片段翻拍",
    "timestamp": 1781050512,
    "hot": 8659545,
    "url": "https://p5-ex-gddgtc-sign.douyinpic.com/tos-cn-p-0015c000-ce/o8AGnRIwnNAiXif7YoexyEvOavBsEBdIkF41Tn~noop.jpeg?lk3s=bfd515bb&x-expires=1781092800&x-signature=k6oXuT%2BW2HQMfj6N3PRayCZ5ei8%3D&from=3218412987",
    "mobileUrl": "https://p5-ex-gddgtc-sign.douyinpic.com/tos-cn-p-0015c000-ce/o8AGnRIwnNAiXif7YoexyEvOavBsEBdIkF41Tn~noop.jpeg?lk3s=bfd515bb&x-expires=1781092800&x-signature=k6oXuT%2BW2HQMfj6N3PRayCZ5ei8%3D&from=3218412987"
  },
  {
    "id": "2529064",
    "title": "成长中你对哪个词的理解变了",
    "timestamp": 1781019590,
    "hot": 8424066,
    "url": "https://p3-sign.douyinpic.com/tos-cn-i-0813c001/oYgIxiPAaADI0HhEVbxjA1PQAAA1ilV0VWAiB~noop.jpeg?lk3s=bfd515bb&x-expires=1781092800&x-signature=x0%2F6d09tgO1oZCf1a6iLALAirb8%3D&from=3218412987",
    "mobileUrl": "https://p3-sign.douyinpic.com/tos-cn-i-0813c001/oYgIxiPAaADI0HhEVbxjA1PQAAA1ilV0VWAiB~noop.jpeg?lk3s=bfd515bb&x-expires=1781092800&x-signature=x0%2F6d09tgO1oZCf1a6iLALAirb8%3D&from=3218412987"
  },
  {
    "id": "2528751",
    "title": "张桂梅作废了之前的狠话",
    "timestamp": 1781000780,
    "hot": 8251606,
    "url": "https://p3-sign.douyinpic.com/tos-cn-p-0015/ocDDITOaEcJDIuFgqqwAi39fe7z9BiAJnIAjb9~noop.jpeg?lk3s=bfd515bb&x-expires=1781092800&x-signature=Z6yE6o0r9S49BDvmXF06Q6g33nM%3D&from=3218412987",
    "mobileUrl": "https://p3-sign.douyinpic.com/tos-cn-p-0015/ocDDITOaEcJDIuFgqqwAi39fe7z9BiAJnIAjb9~noop.jpeg?lk3s=bfd515bb&x-expires=1781092800&x-signature=Z6yE6o0r9S49BDvmXF06Q6g33nM%3D&from=3218412987"
  },
  {
    "id": "2528731",
    "title": "还好你比我舍得",
    "timestamp": 1780999807,
    "hot": 8122503,
    "url": "https://p26-sign.douyinpic.com/tos-cn-i-0813/ocmAJQAzigUAZjwiBIIGadViEAtAECLSvgIAP~noop.jpeg?lk3s=bfd515bb&x-expires=1781092800&x-signature=Q3H%2BEhTWJQ4GSKsRT%2FPR4Kij1ok%3D&from=3218412987",
    "mobileUrl": "https://p26-sign.douyinpic.com/tos-cn-i-0813/ocmAJQAzigUAZjwiBIIGadViEAtAECLSvgIAP~noop.jpeg?lk3s=bfd515bb&x-expires=1781092800&x-signature=Q3H%2BEhTWJQ4GSKsRT%2FPR4Kij1ok%3D&from=3218412987"
  },
  {
    "id": "2529311",
    "title": "A股半导体板块逆市爆发",
    "timestamp": 1781061578,
    "hot": 8041804,
    "url": "https://p5-ex-gddgtc-sign.douyinpic.com/tos-cn-p-0015/oYDRp5iIIAg1UiFfI0iDo30B5ikVrAAnBBGeEx~noop.jpeg?lk3s=bfd515bb&x-expires=1781092800&x-signature=LsptS7e5P8onVRVCllkA63rz5G0%3D&from=3218412987",
    "mobileUrl": "https://p5-ex-gddgtc-sign.douyinpic.com/tos-cn-p-0015/oYDRp5iIIAg1UiFfI0iDo30B5ikVrAAnBBGeEx~noop.jpeg?lk3s=bfd515bb&x-expires=1781092800&x-signature=LsptS7e5P8onVRVCllkA63rz5G0%3D&from=3218412987"
  },
  {
    "id": "2529077",
    "title": "紫色才是公主风本命配色",
    "timestamp": 1781046460,
    "hot": 7829551,
    "url": "https://p11-sign.douyinpic.com/tos-cn-p-0015/oYE9vhQLtRP26yDFBgfwFmANK8QJ7aepAYJqHA~noop.jpeg?lk3s=bfd515bb&x-expires=1781092800&x-signature=gi4Nkn%2FIWd9AfDd6ksHRGWcUuxE%3D&from=3218412987",
    "mobileUrl": "https://p11-sign.douyinpic.com/tos-cn-p-0015/oYE9vhQLtRP26yDFBgfwFmANK8QJ7aepAYJqHA~noop.jpeg?lk3s=bfd515bb&x-expires=1781092800&x-signature=gi4Nkn%2FIWd9AfDd6ksHRGWcUuxE%3D&from=3218412987"
  },
  {
    "id": "2529069",
    "title": "我愿意做你的Emily",
    "timestamp": 1781029855,
    "hot": 7821114,
    "url": "https://p11-sign.douyinpic.com/tos-cn-i-0813c001/oABBJnDzFAqeToP2A7M8AEKBVnnIQEAfAU6YfE~noop.jpeg?lk3s=bfd515bb&x-expires=1781092800&x-signature=7nLneQKfphOphtdaAGXECHhQoyk%3D&from=3218412987",
    "mobileUrl": "https://p11-sign.douyinpic.com/tos-cn-i-0813c001/oABBJnDzFAqeToP2A7M8AEKBVnnIQEAfAU6YfE~noop.jpeg?lk3s=bfd515bb&x-expires=1781092800&x-signature=7nLneQKfphOphtdaAGXECHhQoyk%3D&from=3218412987"
  },
  {
    "id": "2529054",
    "title": "Angel手语舞挑战",
    "timestamp": 1781017640,
    "hot": 7806261,
    "url": "https://p11-sign.douyinpic.com/tos-cn-i-0813c000-ce/oAATA7LPeQoQfKoAvBDeCIf7gn42EOFAATSD0v~noop.jpeg?lk3s=bfd515bb&x-expires=1781092800&x-signature=WC%2Fa54pYFd5K1RtCUhMZcp9H%2FEs%3D&from=3218412987",
    "mobileUrl": "https://p11-sign.douyinpic.com/tos-cn-i-0813c000-ce/oAATA7LPeQoQfKoAvBDeCIf7gn42EOFAATSD0v~noop.jpeg?lk3s=bfd515bb&x-expires=1781092800&x-signature=WC%2Fa54pYFd5K1RtCUhMZcp9H%2FEs%3D&from=3218412987"
  },
  {
    "id": "2528875",
    "title": "传了三代的学步车全是智慧",
    "timestamp": 1781007308,
    "hot": 7805951,
    "url": "https://p26-sign.douyinpic.com/tos-cn-p-0015/oYFnhuliPdeREICIXBi1A5gBgHNkJAVaPfEA84~noop.jpeg?lk3s=bfd515bb&x-expires=1781092800&x-signature=AGVzLqCLeQAIdgaRBTBseMfZxTw%3D&from=3218412987",
    "mobileUrl": "https://p26-sign.douyinpic.com/tos-cn-p-0015/oYFnhuliPdeREICIXBi1A5gBgHNkJAVaPfEA84~noop.jpeg?lk3s=bfd515bb&x-expires=1781092800&x-signature=AGVzLqCLeQAIdgaRBTBseMfZxTw%3D&from=3218412987"
  },
  {
    "id": "2529316",
    "title": "黄晓明拟录取上戏博士",
    "timestamp": 1781061742,
    "hot": 7788584,
    "url": "https://p3-sign.douyinpic.com/tos-cn-p-0015/oMG3CLeG0g582YoDhPeQyoHzjEfAKIfALP5bgA~noop.jpeg?lk3s=bfd515bb&x-expires=1781092800&x-signature=hpCVfaVPHX9gtPY6zU7I5J5Td2M%3D&from=3218412987",
    "mobileUrl": "https://p3-sign.douyinpic.com/tos-cn-p-0015/oMG3CLeG0g582YoDhPeQyoHzjEfAKIfALP5bgA~noop.jpeg?lk3s=bfd515bb&x-expires=1781092800&x-signature=hpCVfaVPHX9gtPY6zU7I5J5Td2M%3D&from=3218412987"
  },
  {
    "id": "2528709",
    "title": "多地高考结束",
    "timestamp": 1780998723,
    "hot": 7782507,
    "url": "https://p3-sign.douyinpic.com/obj/webcast-cover/7648897003523050275?lk3s=bfd515bb&x-expires=1781092800&x-signature=eU9%2Fllg3FsnaDwWt3sHFaQ3t5qo%3D&from=3218412987",
    "mobileUrl": "https://p3-sign.douyinpic.com/obj/webcast-cover/7648897003523050275?lk3s=bfd515bb&x-expires=1781092800&x-signature=eU9%2Fllg3FsnaDwWt3sHFaQ3t5qo%3D&from=3218412987"
  },
  {
    "id": "2528593",
    "title": "跟着姜乘澜学画毕业上镜妆",
    "timestamp": 1780993600,
    "hot": 7771184,
    "url": "https://p5-ex-gddgtc-sign.douyinpic.com/tos-cn-p-0015/o8Fn9qzfJcFEAvpQAAIZSktfzC5gvFIDCKDBm7~noop.jpeg?lk3s=bfd515bb&x-expires=1781092800&x-signature=L9SKlOvDSeBtK%2FH5gPJGXpVa7js%3D&from=3218412987",
    "mobileUrl": "https://p5-ex-gddgtc-sign.douyinpic.com/tos-cn-p-0015/o8Fn9qzfJcFEAvpQAAIZSktfzC5gvFIDCKDBm7~noop.jpeg?lk3s=bfd515bb&x-expires=1781092800&x-signature=L9SKlOvDSeBtK%2FH5gPJGXpVa7js%3D&from=3218412987"
  },
  {
    "id": "2528789",
    "title": "盛世天下女帝篇全球上线",
    "timestamp": 1781003344,
    "hot": 7766343,
    "url": "https://p3-sign.douyinpic.com/tos-cn-p-0015/okfCy4daTCBFv9ZECIYliBAabeeAAUbMDB7nEY~noop.jpeg?lk3s=bfd515bb&x-expires=1781092800&x-signature=qpN0L5CYLecV%2FSMF82ZQI%2FfW%2B%2Fw%3D&from=3218412987",
    "mobileUrl": "https://p3-sign.douyinpic.com/tos-cn-p-0015/okfCy4daTCBFv9ZECIYliBAabeeAAUbMDB7nEY~noop.jpeg?lk3s=bfd515bb&x-expires=1781092800&x-signature=qpN0L5CYLecV%2FSMF82ZQI%2FfW%2B%2Fw%3D&from=3218412987"
  },
  {
    "id": "2529058",
    "title": "电影火遮眼观后感",
    "timestamp": 1781017839,
    "hot": 7766263,
    "url": "https://p11-sign.douyinpic.com/tos-cn-p-0015/ooJrQGE7xMAxyf3LQ8XjB7UD5B9AfCeTQp8qPQ~noop.jpeg?lk3s=bfd515bb&x-expires=1781092800&x-signature=WZQEW9LdkfdRyNRxBO0x7cT%2BnPA%3D&from=3218412987",
    "mobileUrl": "https://p11-sign.douyinpic.com/tos-cn-p-0015/ooJrQGE7xMAxyf3LQ8XjB7UD5B9AfCeTQp8qPQ~noop.jpeg?lk3s=bfd515bb&x-expires=1781092800&x-signature=WZQEW9LdkfdRyNRxBO0x7cT%2BnPA%3D&from=3218412987"
  },
  {
    "id": "2528465",
    "title": "高考后的第一条抖音",
    "timestamp": 1780987844,
    "hot": 7761160,
    "url": "https://p26-sign.douyinpic.com/tos-cn-i-0813/oUAzAqYCimkEAxF9g1IAWEADyigfuBflAAJEQD~noop.jpeg?lk3s=bfd515bb&x-expires=1781092800&x-signature=YehjHwFZcWXMVUcqx4xn6t0gVmI%3D&from=3218412987",
    "mobileUrl": "https://p26-sign.douyinpic.com/tos-cn-i-0813/oUAzAqYCimkEAxF9g1IAWEADyigfuBflAAJEQD~noop.jpeg?lk3s=bfd515bb&x-expires=1781092800&x-signature=YehjHwFZcWXMVUcqx4xn6t0gVmI%3D&from=3218412987"
  },
  {
    "id": "2529062",
    "title": "再也听不到九镑十五便士了",
    "timestamp": 1781018770,
    "hot": 7754351,
    "url": "https://p11-sign.douyinpic.com/tos-cn-p-0015/oMVvOATP3DFN7EQqZJFfABgBWfBl7cQv9kDnAq~noop.jpeg?lk3s=bfd515bb&x-expires=1781092800&x-signature=86AdZ0QpVUALYZSq8Rj1BeXPuRQ%3D&from=3218412987",
    "mobileUrl": "https://p11-sign.douyinpic.com/tos-cn-p-0015/oMVvOATP3DFN7EQqZJFfABgBWfBl7cQv9kDnAq~noop.jpeg?lk3s=bfd515bb&x-expires=1781092800&x-signature=86AdZ0QpVUALYZSq8Rj1BeXPuRQ%3D&from=3218412987"
  },
  {
    "id": "2528613",
    "title": "董路足球小将和苗霖的故事",
    "timestamp": 1780993982,
    "hot": 7752800,
    "url": "https://p5-ex-gddgtc-sign.douyinpic.com/tos-cn-p-0015/okyvKA4JRsMA9e9nqOZfMCCAgETnBTyIJQr7sJ~noop.jpeg?lk3s=bfd515bb&x-expires=1781092800&x-signature=WhN34xyjGgVpmFSxCdxZ%2B5Cbjns%3D&from=3218412987",
    "mobileUrl": "https://p5-ex-gddgtc-sign.douyinpic.com/tos-cn-p-0015/okyvKA4JRsMA9e9nqOZfMCCAgETnBTyIJQr7sJ~noop.jpeg?lk3s=bfd515bb&x-expires=1781092800&x-signature=WhN34xyjGgVpmFSxCdxZ%2B5Cbjns%3D&from=3218412987"
  },
  {
    "id": "2528386",
    "title": "全网最懂足球的人都来懂球大会了",
    "timestamp": 1780984288,
    "hot": 7743338,
    "url": "https://p26-sign.douyinpic.com/tos-cn-p-0015c000-ce/o4ueYzwa3iR0QVV1AMCdImEnvYA4tBEn6B3eEi~noop.jpeg?lk3s=bfd515bb&x-expires=1781092800&x-signature=CkmvZReWAU0ZXlWRGk9MfBzSpgo%3D&from=3218412987",
    "mobileUrl": "https://p26-sign.douyinpic.com/tos-cn-p-0015c000-ce/o4ueYzwa3iR0QVV1AMCdImEnvYA4tBEn6B3eEi~noop.jpeg?lk3s=bfd515bb&x-expires=1781092800&x-signature=CkmvZReWAU0ZXlWRGk9MfBzSpgo%3D&from=3218412987"
  },
  {
    "id": "2528188",
    "title": "我变美的那个夏天",
    "timestamp": 1780973928,
    "hot": 7737476,
    "url": "https://p3-sign.douyinpic.com/tos-cn-i-0813c000-ce/osrAcHAA9FD0AEeAvq2Q91wADEIwfESDQesNAE~noop.jpeg?lk3s=bfd515bb&x-expires=1781092800&x-signature=%2BhBxyvFO6ZDzAOS7Ca3Goo0zd%2FE%3D&from=3218412987",
    "mobileUrl": "https://p3-sign.douyinpic.com/tos-cn-i-0813c000-ce/osrAcHAA9FD0AEeAvq2Q91wADEIwfESDQesNAE~noop.jpeg?lk3s=bfd515bb&x-expires=1781092800&x-signature=%2BhBxyvFO6ZDzAOS7Ca3Goo0zd%2FE%3D&from=3218412987"
  },
  {
    "id": "2529199",
    "title": "鼠牛功夫高虎兔胆气豪",
    "timestamp": 1781057286,
    "hot": 7735579,
    "url": "https://p3-sign.douyinpic.com/tos-cn-i-0813c000-ce/oYAAEa24IEPNVv0g9MaiAmBn5Ki8hAitkAsAz~noop.jpeg?lk3s=bfd515bb&x-expires=1781092800&x-signature=S9ciKJura3dEKNZW1CHqq0Fmtjg%3D&from=3218412987",
    "mobileUrl": "https://p3-sign.douyinpic.com/tos-cn-i-0813c000-ce/oYAAEa24IEPNVv0g9MaiAmBn5Ki8hAitkAsAz~noop.jpeg?lk3s=bfd515bb&x-expires=1781092800&x-signature=S9ciKJura3dEKNZW1CHqq0Fmtjg%3D&from=3218412987"
  },
  {
    "id": "2527254",
    "title": "青春是本写不完的旧书",
    "timestamp": 1780900728,
    "hot": 7729627,
    "url": "https://p3-sign.douyinpic.com/tos-cn-p-0015/okRsdaiPix7zEgAOZw2IApQXSBiJIzGXiBFaP~noop.jpeg?lk3s=bfd515bb&x-expires=1781092800&x-signature=aAJaiJbPXZRmigDgwn5tTTcnktI%3D&from=3218412987",
    "mobileUrl": "https://p3-sign.douyinpic.com/tos-cn-p-0015/okRsdaiPix7zEgAOZw2IApQXSBiJIzGXiBFaP~noop.jpeg?lk3s=bfd515bb&x-expires=1781092800&x-signature=aAJaiJbPXZRmigDgwn5tTTcnktI%3D&from=3218412987"
  },
  {
    "id": "2528721",
    "title": "花儿花儿为谁开",
    "timestamp": 1780999310,
    "hot": 7728043,
    "url": "https://p3-sign.douyinpic.com/tos-cn-i-0813c000-ce/ooiAAiyIvZqZaEziAGJgnMAbBPiBAlA3NaLjx~noop.jpeg?lk3s=bfd515bb&x-expires=1781092800&x-signature=lkjIhfalSwygdmTQ0KL26ibSLyk%3D&from=3218412987",
    "mobileUrl": "https://p3-sign.douyinpic.com/tos-cn-i-0813c000-ce/ooiAAiyIvZqZaEziAGJgnMAbBPiBAlA3NaLjx~noop.jpeg?lk3s=bfd515bb&x-expires=1781092800&x-signature=lkjIhfalSwygdmTQ0KL26ibSLyk%3D&from=3218412987"
  },
  {
    "id": "2528415",
    "title": "一秒找到你的本命眉型",
    "timestamp": 1780985577,
    "hot": 7723775,
    "url": "https://p11-sign.douyinpic.com/tos-cn-p-0015c000-ce/oU7DwXJBBe78YVReqUXNAeOjXmEBISnuMznJQg~noop.jpeg?lk3s=bfd515bb&x-expires=1781092800&x-signature=B8DPvoUtPgdjb6lHQMBn1rcrZa0%3D&from=3218412987",
    "mobileUrl": "https://p11-sign.douyinpic.com/tos-cn-p-0015c000-ce/oU7DwXJBBe78YVReqUXNAeOjXmEBISnuMznJQg~noop.jpeg?lk3s=bfd515bb&x-expires=1781092800&x-signature=B8DPvoUtPgdjb6lHQMBn1rcrZa0%3D&from=3218412987"
  },
  {
    "id": "2528303",
    "title": "穿搭界最严厉的老师来了",
    "timestamp": 1780978536,
    "hot": 7723342,
    "url": "https://p11-sign.douyinpic.com/tos-cn-p-0015c000-ce/osurEfWbBEI1iyjAFmim0kEiECeI9PHw5mesyA~noop.jpeg?lk3s=bfd515bb&x-expires=1781092800&x-signature=hWFHhr5iJQESKyrWrpFMoF4Pgs0%3D&from=3218412987",
    "mobileUrl": "https://p11-sign.douyinpic.com/tos-cn-p-0015c000-ce/osurEfWbBEI1iyjAFmim0kEiECeI9PHw5mesyA~noop.jpeg?lk3s=bfd515bb&x-expires=1781092800&x-signature=hWFHhr5iJQESKyrWrpFMoF4Pgs0%3D&from=3218412987"
  },
  {
    "id": "2528445",
    "title": "拍出夏天电影感",
    "timestamp": 1780986981,
    "hot": 7720529,
    "url": "https://p11-sign.douyinpic.com/tos-cn-i-dy/ddeec810b1fb4b00a76533483d8362d6~noop.jpeg?lk3s=bfd515bb&x-expires=1781092800&x-signature=LW8CkEY8b%2F1NTQBJT8qjeuwX4Zg%3D&from=3218412987",
    "mobileUrl": "https://p11-sign.douyinpic.com/tos-cn-i-dy/ddeec810b1fb4b00a76533483d8362d6~noop.jpeg?lk3s=bfd515bb&x-expires=1781092800&x-signature=LW8CkEY8b%2F1NTQBJT8qjeuwX4Zg%3D&from=3218412987"
  },
  {
    "id": "2529122",
    "title": "大馋丫头vs厌食小狗",
    "timestamp": 1781051684,
    "hot": 7718487,
    "url": "https://p3-sign.douyinpic.com/tos-cn-p-0015/oY3ftQAn8ABHtREeSM2ogxEp7QCIWDU9GfpAft~noop.jpeg?lk3s=bfd515bb&x-expires=1781092800&x-signature=xKbvvZPlUu6r25l0fdWp7%2FiWvn4%3D&from=3218412987",
    "mobileUrl": "https://p3-sign.douyinpic.com/tos-cn-p-0015/oY3ftQAn8ABHtREeSM2ogxEp7QCIWDU9GfpAft~noop.jpeg?lk3s=bfd515bb&x-expires=1781092800&x-signature=xKbvvZPlUu6r25l0fdWp7%2FiWvn4%3D&from=3218412987"
  },
  {
    "id": "2528853",
    "title": "陈坤用方言欢迎大家来重庆耍",
    "timestamp": 1781006583,
    "hot": 7717057,
    "url": "https://p11-sign.douyinpic.com/tos-cn-p-0015/oMEB0AvfAA1NChE32u417oYEfsnrJgDJXzfjsf~noop.jpeg?lk3s=bfd515bb&x-expires=1781092800&x-signature=QEVHoPdcu9ztJzSuSSZSlyDun6k%3D&from=3218412987",
    "mobileUrl": "https://p11-sign.douyinpic.com/tos-cn-p-0015/oMEB0AvfAA1NChE32u417oYEfsnrJgDJXzfjsf~noop.jpeg?lk3s=bfd515bb&x-expires=1781092800&x-signature=QEVHoPdcu9ztJzSuSSZSlyDun6k%3D&from=3218412987"
  },
  {
    "id": "2528666",
    "title": "高考结束后的那个下午",
    "timestamp": 1780996158,
    "hot": 7706906,
    "url": "https://p26-sign.douyinpic.com/tos-cn-p-0015c000-ce/osG1fIGCHQgTdLXBuQyeEf5WWjzSD7g5mUIQAJ~noop.jpeg?lk3s=bfd515bb&x-expires=1781092800&x-signature=VTF%2Bk1J3BeWmFdHFYhOD8Ln8x2U%3D&from=3218412987",
    "mobileUrl": "https://p26-sign.douyinpic.com/tos-cn-p-0015c000-ce/osG1fIGCHQgTdLXBuQyeEf5WWjzSD7g5mUIQAJ~noop.jpeg?lk3s=bfd515bb&x-expires=1781092800&x-signature=VTF%2Bk1J3BeWmFdHFYhOD8Ln8x2U%3D&from=3218412987"
  },
  {
    "id": "2528650",
    "title": "姜辣才是岳阳菜的灵魂",
    "timestamp": 1780995604,
    "hot": 7681807,
    "url": "https://p5-ex-gddgtc-sign.douyinpic.com/tos-cn-p-0015/oUDAPcFJRIDgDeQAGhCgfREZqnIu9JMACBl8wB~noop.jpeg?lk3s=bfd515bb&x-expires=1781092800&x-signature=5KeRg8WKmjU6wBe6aLjOQbfvmsI%3D&from=3218412987",
    "mobileUrl": "https://p5-ex-gddgtc-sign.douyinpic.com/tos-cn-p-0015/oUDAPcFJRIDgDeQAGhCgfREZqnIu9JMACBl8wB~noop.jpeg?lk3s=bfd515bb&x-expires=1781092800&x-signature=5KeRg8WKmjU6wBe6aLjOQbfvmsI%3D&from=3218412987"
  },
  {
    "id": "2529386",
    "title": "和平精英体验服",
    "timestamp": 1781065839,
    "hot": 7680991,
    "url": "https://p26-sign.douyinpic.com/tos-cn-p-0015/ocwdEniq1zC33QVnABBAIVJ59Xqg6BkAOfi8fd~noop.jpeg?lk3s=bfd515bb&x-expires=1781092800&x-signature=MHel0s%2BrFdSWsw5lfxjiYyCM10w%3D&from=3218412987",
    "mobileUrl": "https://p26-sign.douyinpic.com/tos-cn-p-0015/ocwdEniq1zC33QVnABBAIVJ59Xqg6BkAOfi8fd~noop.jpeg?lk3s=bfd515bb&x-expires=1781092800&x-signature=MHel0s%2BrFdSWsw5lfxjiYyCM10w%3D&from=3218412987"
  },
  {
    "id": "2528315",
    "title": "给哈兰德推荐一道中国菜",
    "timestamp": 1780979051,
    "hot": 7679903,
    "url": "https://p11-sign.douyinpic.com/tos-cn-p-0015c000-ce/o4ADEAFqeEnBw9QQwWNfCFZJBDFeiqIxXzGS5w~noop.jpeg?lk3s=bfd515bb&x-expires=1781092800&x-signature=eVU%2BazI5gZR68ElAISU0AL6SFA0%3D&from=3218412987",
    "mobileUrl": "https://p11-sign.douyinpic.com/tos-cn-p-0015c000-ce/o4ADEAFqeEnBw9QQwWNfCFZJBDFeiqIxXzGS5w~noop.jpeg?lk3s=bfd515bb&x-expires=1781092800&x-signature=eVU%2BazI5gZR68ElAISU0AL6SFA0%3D&from=3218412987"
  },
  {
    "id": "2527651",
    "title": "海贼王1165集简评",
    "timestamp": 1780912489,
    "hot": 7677149,
    "url": "https://p5-ex-gddgtc-sign.douyinpic.com/tos-cn-p-0015/oYfabXgJJi21uyKqANBSIqIlflA4aBACFB89Ji~noop.jpeg?lk3s=bfd515bb&x-expires=1781092800&x-signature=DcqsiipXbt9e5kZXAkKO8aiGwBE%3D&from=3218412987",
    "mobileUrl": "https://p5-ex-gddgtc-sign.douyinpic.com/tos-cn-p-0015/oYfabXgJJi21uyKqANBSIqIlflA4aBACFB89Ji~noop.jpeg?lk3s=bfd515bb&x-expires=1781092800&x-signature=DcqsiipXbt9e5kZXAkKO8aiGwBE%3D&from=3218412987"
  },
  {
    "id": "2527604",
    "title": "驻马店老式扣碗简直夯中夯",
    "timestamp": 1780911150,
    "hot": 7671903,
    "url": "https://p3-sign.douyinpic.com/tos-cn-p-0015/ocFYHNiqJAjOAD1LEk5mE9dBNPmfQANeABAgQD~noop.jpeg?lk3s=bfd515bb&x-expires=1781092800&x-signature=eYK9eC2EfMrGk3cEWudV9A99Reo%3D&from=3218412987",
    "mobileUrl": "https://p3-sign.douyinpic.com/tos-cn-p-0015/ocFYHNiqJAjOAD1LEk5mE9dBNPmfQANeABAgQD~noop.jpeg?lk3s=bfd515bb&x-expires=1781092800&x-signature=eYK9eC2EfMrGk3cEWudV9A99Reo%3D&from=3218412987"
  },
  {
    "id": "2527565",
    "title": "看我用早茶拿捏哈兰德",
    "timestamp": 1780910133,
    "hot": 7670953,
    "url": "https://p26-sign.douyinpic.com/tos-cn-p-0015c000-ce/o8WwEEFOqhgecQpmTCDAI7l129oAAGgDdfEffB~noop.jpeg?lk3s=bfd515bb&x-expires=1781092800&x-signature=UqPyipoM62h1ILQ2AEjA354d2ro%3D&from=3218412987",
    "mobileUrl": "https://p26-sign.douyinpic.com/tos-cn-p-0015c000-ce/o8WwEEFOqhgecQpmTCDAI7l129oAAGgDdfEffB~noop.jpeg?lk3s=bfd515bb&x-expires=1781092800&x-signature=UqPyipoM62h1ILQ2AEjA354d2ro%3D&from=3218412987"
  }
]