[
  {
    "id": "2391128",
    "title": "美国伊朗谈判今日举行",
    "timestamp": 1770333426,
    "hot": 12435340,
    "url": "https://p3-sign.douyinpic.com/tos-cn-p-0015/okgSUTWBeCkcfA7mq1gA4LIBcjGQxCO18eAHja~noop.jpeg?lk3s=bfd515bb&x-expires=1770379200&x-signature=hfUceId02RGYgnVlXoAZ%2Fbq3dwY%3D&from=3218412987",
    "mobileUrl": "https://p3-sign.douyinpic.com/tos-cn-p-0015/okgSUTWBeCkcfA7mq1gA4LIBcjGQxCO18eAHja~noop.jpeg?lk3s=bfd515bb&x-expires=1770379200&x-signature=hfUceId02RGYgnVlXoAZ%2Fbq3dwY%3D&from=3218412987"
  },
  {
    "id": "2391185",
    "title": "董亦军被追授时代楷模称号",
    "timestamp": 1770338784,
    "hot": 11455143,
    "url": "https://p26-sign.douyinpic.com/tos-cn-p-0015/oEqY4v9PI4iGw9FAlT4OOaiQB4HIlUPAiIaTQ~noop.jpeg?lk3s=bfd515bb&x-expires=1770379200&x-signature=eeaUYTvFMemsAcLZKZMx02Gk7tw%3D&from=3218412987",
    "mobileUrl": "https://p26-sign.douyinpic.com/tos-cn-p-0015/oEqY4v9PI4iGw9FAlT4OOaiQB4HIlUPAiIaTQ~noop.jpeg?lk3s=bfd515bb&x-expires=1770379200&x-signature=eeaUYTvFMemsAcLZKZMx02Gk7tw%3D&from=3218412987"
  },
  {
    "id": "2391318",
    "title": "“反向过年”成为新潮",
    "timestamp": 1770348501,
    "hot": 11153176,
    "url": "https://p11-sign.douyinpic.com/tos-cn-p-0015/o0BTsSQPG6zU8p5IaEiiZMFaGpI7vLYAOAINM~noop.jpeg?lk3s=bfd515bb&x-expires=1770379200&x-signature=bgSQdla7h6E6AmJDu%2FSpjjZ3uF8%3D&from=3218412987",
    "mobileUrl": "https://p11-sign.douyinpic.com/tos-cn-p-0015/o0BTsSQPG6zU8p5IaEiiZMFaGpI7vLYAOAINM~noop.jpeg?lk3s=bfd515bb&x-expires=1770379200&x-signature=bgSQdla7h6E6AmJDu%2FSpjjZ3uF8%3D&from=3218412987"
  },
  {
    "id": "2390985",
    "title": "苏翊鸣晋级大跳台决赛",
    "timestamp": 1770293232,
    "hot": 11151272,
    "url": "https://p11-sign.douyinpic.com/tos-cn-p-0015/oYAp9VQgDyAF4EUQ289vygfbfMDLAB6QsBypxB~noop.jpeg?lk3s=bfd515bb&x-expires=1770379200&x-signature=3hH4dcnuFTyzPGzpAsM8zYh2Uig%3D&from=3218412987",
    "mobileUrl": "https://p11-sign.douyinpic.com/tos-cn-p-0015/oYAp9VQgDyAF4EUQ289vygfbfMDLAB6QsBypxB~noop.jpeg?lk3s=bfd515bb&x-expires=1770379200&x-signature=3hH4dcnuFTyzPGzpAsM8zYh2Uig%3D&from=3218412987"
  },
  {
    "id": "2391320",
    "title": "橘时到吉时到",
    "timestamp": 1770348579,
    "hot": 10554965,
    "url": "https://p3-sign.douyinpic.com/tos-cn-p-0015c000-ce/oEaAyBE3VwDs9VwW4K3JFtrEffoDFpIAgtECoE~noop.jpeg?lk3s=bfd515bb&x-expires=1770379200&x-signature=H92kU832%2FJ3VqysVwE4x%2BdkAH4c%3D&from=3218412987",
    "mobileUrl": "https://p3-sign.douyinpic.com/tos-cn-p-0015c000-ce/oEaAyBE3VwDs9VwW4K3JFtrEffoDFpIAgtECoE~noop.jpeg?lk3s=bfd515bb&x-expires=1770379200&x-signature=H92kU832%2FJ3VqysVwE4x%2BdkAH4c%3D&from=3218412987"
  },
  {
    "id": "2391069",
    "title": "这届精选创作者宠粉太全面了",
    "timestamp": 1770299987,
    "hot": 10244973,
    "url": "https://p3-sign.douyinpic.com/tos-cn-p-0015/o0OfGFdvA309vD3hIJZAkj7fCHEAgp1CgCBAIi~noop.jpeg?lk3s=bfd515bb&x-expires=1770379200&x-signature=hcC21VsUj25svuIFaAQ1LLVwdtc%3D&from=3218412987",
    "mobileUrl": "https://p3-sign.douyinpic.com/tos-cn-p-0015/o0OfGFdvA309vD3hIJZAkj7fCHEAgp1CgCBAIi~noop.jpeg?lk3s=bfd515bb&x-expires=1770379200&x-signature=hcC21VsUj25svuIFaAQ1LLVwdtc%3D&from=3218412987"
  },
  {
    "id": "2391361",
    "title": "留子回国过年吃啥都香",
    "timestamp": 1770350292,
    "hot": 9158790,
    "url": "https://p11-sign.douyinpic.com/tos-cn-p-0015c000-ce/oUekgIQ7iBeUk4GtJbgLDApqQeh6TnID6FHHCA~noop.jpeg?lk3s=bfd515bb&x-expires=1770379200&x-signature=hEEUzGVWqYlQDoSnAEldIjhCjv0%3D&from=3218412987",
    "mobileUrl": "https://p11-sign.douyinpic.com/tos-cn-p-0015c000-ce/oUekgIQ7iBeUk4GtJbgLDApqQeh6TnID6FHHCA~noop.jpeg?lk3s=bfd515bb&x-expires=1770379200&x-signature=hEEUzGVWqYlQDoSnAEldIjhCjv0%3D&from=3218412987"
  },
  {
    "id": "2391236",
    "title": "海南省委原秘书长倪强被双开",
    "timestamp": 1770343440,
    "hot": 9149219,
    "url": "https://p3-sign.douyinpic.com/tos-cn-p-0015/oQpTCVazIpOLsoLAnAfgCM5M7ZyGGBlgBeegWa~noop.jpeg?lk3s=bfd515bb&x-expires=1770379200&x-signature=YJfO6Oy0BvrqaM6UdwKuH3dkIS8%3D&from=3218412987",
    "mobileUrl": "https://p3-sign.douyinpic.com/tos-cn-p-0015/oQpTCVazIpOLsoLAnAfgCM5M7ZyGGBlgBeegWa~noop.jpeg?lk3s=bfd515bb&x-expires=1770379200&x-signature=YJfO6Oy0BvrqaM6UdwKuH3dkIS8%3D&from=3218412987"
  },
  {
    "id": "2390733",
    "title": "冬日跑步装备大赏",
    "timestamp": 1770283245,
    "hot": 9120386,
    "url": "https://p3-sign.douyinpic.com/tos-cn-p-0015c000-ce/owiBAeCERgC7GY5QFk8IApDQFJCLIJ0fTbs3eq~noop.jpeg?lk3s=bfd515bb&x-expires=1770379200&x-signature=tbEJVJZm3T8H4MFRmyB8vQN4QuE%3D&from=3218412987",
    "mobileUrl": "https://p3-sign.douyinpic.com/tos-cn-p-0015c000-ce/owiBAeCERgC7GY5QFk8IApDQFJCLIJ0fTbs3eq~noop.jpeg?lk3s=bfd515bb&x-expires=1770379200&x-signature=tbEJVJZm3T8H4MFRmyB8vQN4QuE%3D&from=3218412987"
  },
  {
    "id": "2391134",
    "title": "媒体：立陶宛嘴上认错还不够",
    "timestamp": 1770333533,
    "hot": 9096017,
    "url": "https://p3-sign.douyinpic.com/tos-cn-p-0015/ooIp0AI6EDBugqAvINGABDrFtCimewdi1sTNf2~noop.jpeg?lk3s=bfd515bb&x-expires=1770379200&x-signature=DeBxJjrG1gSkZRkOTevU91xsy5k%3D&from=3218412987",
    "mobileUrl": "https://p3-sign.douyinpic.com/tos-cn-p-0015/ooIp0AI6EDBugqAvINGABDrFtCimewdi1sTNf2~noop.jpeg?lk3s=bfd515bb&x-expires=1770379200&x-signature=DeBxJjrG1gSkZRkOTevU91xsy5k%3D&from=3218412987"
  },
  {
    "id": "2390589",
    "title": "中方回应长和集团将发起国际仲裁",
    "timestamp": 1770278506,
    "hot": 9086731,
    "url": "https://p26-sign.douyinpic.com/tos-cn-p-0015/o4LarMdTCA2FBz3PId4JM7lCafIeQECzBMeAQG~noop.jpeg?lk3s=bfd515bb&x-expires=1770379200&x-signature=ioYACoAb5H76jKaLwqp1Q4r%2FDe0%3D&from=3218412987",
    "mobileUrl": "https://p26-sign.douyinpic.com/tos-cn-p-0015/o4LarMdTCA2FBz3PId4JM7lCafIeQECzBMeAQG~noop.jpeg?lk3s=bfd515bb&x-expires=1770379200&x-signature=ioYACoAb5H76jKaLwqp1Q4r%2FDe0%3D&from=3218412987"
  },
  {
    "id": "2391292",
    "title": "重庆市政协原副主席段成刚被公诉",
    "timestamp": 1770346921,
    "hot": 9047060,
    "url": "https://p3-sign.douyinpic.com/tos-cn-p-0015/oET0INUH7BAnWFKpqqi2Ae0HuA1gxBTwI1fpFi~noop.jpeg?lk3s=bfd515bb&x-expires=1770379200&x-signature=scdk9G%2Fjkp52T0KIap92MkRxJ4U%3D&from=3218412987",
    "mobileUrl": "https://p3-sign.douyinpic.com/tos-cn-p-0015/oET0INUH7BAnWFKpqqi2Ae0HuA1gxBTwI1fpFi~noop.jpeg?lk3s=bfd515bb&x-expires=1770379200&x-signature=scdk9G%2Fjkp52T0KIap92MkRxJ4U%3D&from=3218412987"
  },
  {
    "id": "2391235",
    "title": "专家辟谣“一瓶饮料快速解酒”",
    "timestamp": 1770343218,
    "hot": 8899661,
    "url": "https://p3-sign.douyinpic.com/tos-cn-p-0015/oAIIbnaXgkrD0QBEoHeGeC02gfALIF5AAEfmgm~noop.jpeg?lk3s=bfd515bb&x-expires=1770379200&x-signature=BTYuhcc54MmXPU%2FbSptCyDd3ydw%3D&from=3218412987",
    "mobileUrl": "https://p3-sign.douyinpic.com/tos-cn-p-0015/oAIIbnaXgkrD0QBEoHeGeC02gfALIF5AAEfmgm~noop.jpeg?lk3s=bfd515bb&x-expires=1770379200&x-signature=BTYuhcc54MmXPU%2FbSptCyDd3ydw%3D&from=3218412987"
  },
  {
    "id": "2391220",
    "title": "A股",
    "timestamp": 1770341995,
    "hot": 8895183,
    "url": "https://p26-sign.douyinpic.com/obj/webcast-cover/7603214658228652842?lk3s=bfd515bb&x-expires=1770379200&x-signature=lp9%2FPnNRCXFANxoAjvZbWvQ745A%3D&from=3218412987",
    "mobileUrl": "https://p26-sign.douyinpic.com/obj/webcast-cover/7603214658228652842?lk3s=bfd515bb&x-expires=1770379200&x-signature=lp9%2FPnNRCXFANxoAjvZbWvQ745A%3D&from=3218412987"
  },
  {
    "id": "2391091",
    "title": "我的刀盾",
    "timestamp": 1770303224,
    "hot": 8752347,
    "url": "https://p3-sign.douyinpic.com/tos-cn-p-0015/oQYyafAHEEsFyg0ALtpAADrBgI5pCJIfgAiFa9~noop.jpeg?lk3s=bfd515bb&x-expires=1770379200&x-signature=Qkj3EqfEw8rsHJVIDh%2B00U5PF%2FA%3D&from=3218412987",
    "mobileUrl": "https://p3-sign.douyinpic.com/tos-cn-p-0015/oQYyafAHEEsFyg0ALtpAADrBgI5pCJIfgAiFa9~noop.jpeg?lk3s=bfd515bb&x-expires=1770379200&x-signature=Qkj3EqfEw8rsHJVIDh%2B00U5PF%2FA%3D&from=3218412987"
  },
  {
    "id": "2391427",
    "title": "湖人终结76人5连胜",
    "timestamp": 1770355833,
    "hot": 8654606,
    "url": "https://p3-sign.douyinpic.com/tos-cn-p-0015c000-ce/oETIwE4B9OkEpAdfF1QhuXALrfuDABF8nLBEiR~noop.jpeg?lk3s=bfd515bb&x-expires=1770379200&x-signature=V5p%2Fb3mroUHOo%2FdG77fqldCBT3A%3D&from=3218412987",
    "mobileUrl": "https://p3-sign.douyinpic.com/tos-cn-p-0015c000-ce/oETIwE4B9OkEpAdfF1QhuXALrfuDABF8nLBEiR~noop.jpeg?lk3s=bfd515bb&x-expires=1770379200&x-signature=V5p%2Fb3mroUHOo%2FdG77fqldCBT3A%3D&from=3218412987"
  },
  {
    "id": "2391003",
    "title": "李佩仪目睹闺蜜自杀",
    "timestamp": 1770294188,
    "hot": 8631777,
    "url": "https://p26-sign.douyinpic.com/tos-cn-p-0015/oMAUNFDm9AAilIHq1EEI2gBACFegDjRshpf5hy~noop.jpeg?lk3s=bfd515bb&x-expires=1770379200&x-signature=YpgLgdCqxDP1%2FV4uHKXOURhwh0g%3D&from=3218412987",
    "mobileUrl": "https://p26-sign.douyinpic.com/tos-cn-p-0015/oMAUNFDm9AAilIHq1EEI2gBACFegDjRshpf5hy~noop.jpeg?lk3s=bfd515bb&x-expires=1770379200&x-signature=YpgLgdCqxDP1%2FV4uHKXOURhwh0g%3D&from=3218412987"
  },
  {
    "id": "2391073",
    "title": "商业航天何以“一飞冲天”",
    "timestamp": 1770300554,
    "hot": 8630397,
    "url": "https://p3-sign.douyinpic.com/tos-cn-p-0015/ogTxN0C4iGVPAi9tjFCIsgA5xutuBlBzAIufev~noop.jpeg?lk3s=bfd515bb&x-expires=1770379200&x-signature=ZCe8t%2BCrccq3%2BeEWSgZOvJLWwAE%3D&from=3218412987",
    "mobileUrl": "https://p3-sign.douyinpic.com/tos-cn-p-0015/ogTxN0C4iGVPAi9tjFCIsgA5xutuBlBzAIufev~noop.jpeg?lk3s=bfd515bb&x-expires=1770379200&x-signature=ZCe8t%2BCrccq3%2BeEWSgZOvJLWwAE%3D&from=3218412987"
  },
  {
    "id": "2390559",
    "title": "外交部回应普京计划访华",
    "timestamp": 1770277226,
    "hot": 8489613,
    "url": "https://p3-sign.douyinpic.com/tos-cn-p-0015/ocEEIABA7R6CAzGTfLWEefzpJ4jBDI8AEXIwCD~noop.jpeg?lk3s=bfd515bb&x-expires=1770379200&x-signature=obby2z1u3Vxgf7r4PA%2F%2FrGZ50A8%3D&from=3218412987",
    "mobileUrl": "https://p3-sign.douyinpic.com/tos-cn-p-0015/ocEEIABA7R6CAzGTfLWEefzpJ4jBDI8AEXIwCD~noop.jpeg?lk3s=bfd515bb&x-expires=1770379200&x-signature=obby2z1u3Vxgf7r4PA%2F%2FrGZ50A8%3D&from=3218412987"
  },
  {
    "id": "2391346",
    "title": "网剧成何体统开播",
    "timestamp": 1770349425,
    "hot": 7879599,
    "url": "https://p11-sign.douyinpic.com/tos-cn-p-0015/oMLAQI6wIMYiymIAtU7iPwSPaBlCvsQiraE4r~noop.jpeg?lk3s=bfd515bb&x-expires=1770379200&x-signature=QqHDK9kDOjsF%2FQuapGy%2FyVl9jsE%3D&from=3218412987",
    "mobileUrl": "https://p11-sign.douyinpic.com/tos-cn-p-0015/oMLAQI6wIMYiymIAtU7iPwSPaBlCvsQiraE4r~noop.jpeg?lk3s=bfd515bb&x-expires=1770379200&x-signature=QqHDK9kDOjsF%2FQuapGy%2FyVl9jsE%3D&from=3218412987"
  },
  {
    "id": "2390766",
    "title": "郑泽晖任深圳市副市长",
    "timestamp": 1770284201,
    "hot": 7846358,
    "url": "https://p26-sign.douyinpic.com/tos-cn-p-0015/oMfJYG6ChBAFTMzICIx1euACaWLgwpPqDA9EEq~noop.jpeg?lk3s=bfd515bb&x-expires=1770379200&x-signature=tG6hZLvjBpWRyfAivPqhq3BV1t0%3D&from=3218412987",
    "mobileUrl": "https://p26-sign.douyinpic.com/tos-cn-p-0015/oMfJYG6ChBAFTMzICIx1euACaWLgwpPqDA9EEq~noop.jpeg?lk3s=bfd515bb&x-expires=1770379200&x-signature=tG6hZLvjBpWRyfAivPqhq3BV1t0%3D&from=3218412987"
  },
  {
    "id": "2391328",
    "title": "分身搭子陪你过大年",
    "timestamp": 1770348934,
    "hot": 7785717,
    "url": "https://p26-sign.douyinpic.com/tos-cn-p-0015c000-ce/osq4EAUlLoFFpEQpehFfEBwA2unXtYQS9xD3Aq~noop.jpeg?lk3s=bfd515bb&x-expires=1770379200&x-signature=eIKLQxZZVKGsXzheoZ6dpdJKIBU%3D&from=3218412987",
    "mobileUrl": "https://p26-sign.douyinpic.com/tos-cn-p-0015c000-ce/osq4EAUlLoFFpEQpehFfEBwA2unXtYQS9xD3Aq~noop.jpeg?lk3s=bfd515bb&x-expires=1770379200&x-signature=eIKLQxZZVKGsXzheoZ6dpdJKIBU%3D&from=3218412987"
  },
  {
    "id": "2391408",
    "title": "邓超终于有抖音了",
    "timestamp": 1770354347,
    "hot": 7775533,
    "url": "https://p26-sign.douyinpic.com/tos-cn-p-0015c000-ce/oAGFbOOrIDeCFEIoDe7XBikJ9h2ergK8AKAmLT~noop.jpeg?lk3s=bfd515bb&x-expires=1770379200&x-signature=hnasiSlVYJ%2BVgaBvApvERmbe3Zw%3D&from=3218412987",
    "mobileUrl": "https://p26-sign.douyinpic.com/tos-cn-p-0015c000-ce/oAGFbOOrIDeCFEIoDe7XBikJ9h2ergK8AKAmLT~noop.jpeg?lk3s=bfd515bb&x-expires=1770379200&x-signature=hnasiSlVYJ%2BVgaBvApvERmbe3Zw%3D&from=3218412987"
  },
  {
    "id": "2390713",
    "title": "盘点生命树的隐藏剧情线",
    "timestamp": 1770282508,
    "hot": 7774412,
    "url": "https://p26-sign.douyinpic.com/tos-cn-p-0015/oMeyFDLEwZI1gCUpAJBI9BSFNf2vYcADADgBgA~noop.jpeg?lk3s=bfd515bb&x-expires=1770379200&x-signature=zsAbbDiHswY53sxBYPSMxh9C38c%3D&from=3218412987",
    "mobileUrl": "https://p26-sign.douyinpic.com/tos-cn-p-0015/oMeyFDLEwZI1gCUpAJBI9BSFNf2vYcADADgBgA~noop.jpeg?lk3s=bfd515bb&x-expires=1770379200&x-signature=zsAbbDiHswY53sxBYPSMxh9C38c%3D&from=3218412987"
  },
  {
    "id": "2391269",
    "title": "大主宰2武祖林动惊喜登场",
    "timestamp": 1770345940,
    "hot": 7758737,
    "url": "https://p3-sign.douyinpic.com/tos-cn-p-0015/o41TgrQueAgdQ7fFAgLwB9EGDexwHPvIBBCsGg~noop.jpeg?lk3s=bfd515bb&x-expires=1770379200&x-signature=%2FRKzGvAbszTNeXTt1isriJt5tH4%3D&from=3218412987",
    "mobileUrl": "https://p3-sign.douyinpic.com/tos-cn-p-0015/o41TgrQueAgdQ7fFAgLwB9EGDexwHPvIBBCsGg~noop.jpeg?lk3s=bfd515bb&x-expires=1770379200&x-signature=%2FRKzGvAbszTNeXTt1isriJt5tH4%3D&from=3218412987"
  },
  {
    "id": "2391215",
    "title": "蔡徐坤全新专辑听后感",
    "timestamp": 1770341453,
    "hot": 7753051,
    "url": "https://p26-sign.douyinpic.com/tos-cn-p-0015/o0lA5cFhBQDa7iGA8ACgfEEppJQf9IAAC3oJPB~noop.jpeg?lk3s=bfd515bb&x-expires=1770379200&x-signature=rxaHUtLNVrpxFuJ8mECsBX0lHfg%3D&from=3218412987",
    "mobileUrl": "https://p26-sign.douyinpic.com/tos-cn-p-0015/o0lA5cFhBQDa7iGA8ACgfEEppJQf9IAAC3oJPB~noop.jpeg?lk3s=bfd515bb&x-expires=1770379200&x-signature=rxaHUtLNVrpxFuJ8mECsBX0lHfg%3D&from=3218412987"
  },
  {
    "id": "2391034",
    "title": "夜色正浓高质感太顶了",
    "timestamp": 1770296948,
    "hot": 7752167,
    "url": "https://p26-sign.douyinpic.com/tos-cn-p-0015c000-ce/oo6ePIQIcfIaEVmmA7CQ24JLle8peKDcTGWGAX~noop.jpeg?lk3s=bfd515bb&x-expires=1770379200&x-signature=a9sqKOUlxtk7HBCxq0vyFMkY0HI%3D&from=3218412987",
    "mobileUrl": "https://p26-sign.douyinpic.com/tos-cn-p-0015c000-ce/oo6ePIQIcfIaEVmmA7CQ24JLle8peKDcTGWGAX~noop.jpeg?lk3s=bfd515bb&x-expires=1770379200&x-signature=a9sqKOUlxtk7HBCxq0vyFMkY0HI%3D&from=3218412987"
  },
  {
    "id": "2391340",
    "title": "电影惊蛰无声全员有嫌疑",
    "timestamp": 1770349293,
    "hot": 7740953,
    "url": "https://p3-sign.douyinpic.com/tos-cn-p-0015/osswBf9BAiVCIg93ZE0giBLEImenAxBnKAk8t5~noop.jpeg?lk3s=bfd515bb&x-expires=1770379200&x-signature=JDSCIG9za5mFerPk3Z0%2BarHfTbI%3D&from=3218412987",
    "mobileUrl": "https://p3-sign.douyinpic.com/tos-cn-p-0015/osswBf9BAiVCIg93ZE0giBLEImenAxBnKAk8t5~noop.jpeg?lk3s=bfd515bb&x-expires=1770379200&x-signature=JDSCIG9za5mFerPk3Z0%2BarHfTbI%3D&from=3218412987"
  },
  {
    "id": "2391335",
    "title": "飞驰3沈腾沙溢打球各有各的好笑",
    "timestamp": 1770349235,
    "hot": 7739346,
    "url": "https://p3-sign.douyinpic.com/tos-cn-p-0015/ogzDFCEnWBqQ9kfJQE7fEfYnGbCbTQASKBq7A9~noop.jpeg?lk3s=bfd515bb&x-expires=1770379200&x-signature=HbwL0s9dpcJgrJhbGVtExxQGhkU%3D&from=3218412987",
    "mobileUrl": "https://p3-sign.douyinpic.com/tos-cn-p-0015/ogzDFCEnWBqQ9kfJQE7fEfYnGbCbTQASKBq7A9~noop.jpeg?lk3s=bfd515bb&x-expires=1770379200&x-signature=HbwL0s9dpcJgrJhbGVtExxQGhkU%3D&from=3218412987"
  },
  {
    "id": "2391105",
    "title": "当困难来临的时候",
    "timestamp": 1770304254,
    "hot": 7738949,
    "url": "https://p3-sign.douyinpic.com/tos-cn-p-0015c000-ce/owA0RbVA9QrAPomfyaQETEDpe6uFEE1IBw9Agg~noop.jpeg?lk3s=bfd515bb&x-expires=1770379200&x-signature=Y9yktSik73%2BXqfr2HwjJ04fUz9Q%3D&from=3218412987",
    "mobileUrl": "https://p3-sign.douyinpic.com/tos-cn-p-0015c000-ce/owA0RbVA9QrAPomfyaQETEDpe6uFEE1IBw9Agg~noop.jpeg?lk3s=bfd515bb&x-expires=1770379200&x-signature=Y9yktSik73%2BXqfr2HwjJ04fUz9Q%3D&from=3218412987"
  },
  {
    "id": "2391079",
    "title": "美众议院上演骂战",
    "timestamp": 1770301096,
    "hot": 7733962,
    "url": "https://p26-sign.douyinpic.com/tos-cn-p-0015/oMA2AAIpDE1Cx9ZIBoEfBFohKD8aLKI1errlIg~noop.jpeg?lk3s=bfd515bb&x-expires=1770379200&x-signature=3GF7yRcM7sHxld%2BdJI3%2F4sc9u8U%3D&from=3218412987",
    "mobileUrl": "https://p26-sign.douyinpic.com/tos-cn-p-0015/oMA2AAIpDE1Cx9ZIBoEfBFohKD8aLKI1errlIg~noop.jpeg?lk3s=bfd515bb&x-expires=1770379200&x-signature=3GF7yRcM7sHxld%2BdJI3%2F4sc9u8U%3D&from=3218412987"
  },
  {
    "id": "2391164",
    "title": "马斯克怒批西班牙首相",
    "timestamp": 1770336854,
    "hot": 7715946,
    "url": "https://p3-sign.douyinpic.com/tos-cn-p-0015/owA4aP4AIiYAQIObBRHu7EBTBGSPpNsvVgEai~noop.jpeg?lk3s=bfd515bb&x-expires=1770379200&x-signature=fhO0Xn4%2BilLr%2BcXb1%2BZ4I83BXC0%3D&from=3218412987",
    "mobileUrl": "https://p3-sign.douyinpic.com/tos-cn-p-0015/owA4aP4AIiYAQIObBRHu7EBTBGSPpNsvVgEai~noop.jpeg?lk3s=bfd515bb&x-expires=1770379200&x-signature=fhO0Xn4%2BilLr%2BcXb1%2BZ4I83BXC0%3D&from=3218412987"
  },
  {
    "id": "2391397",
    "title": "恋与深空喜迎财神",
    "timestamp": 1770352539,
    "hot": 7715234,
    "url": "https://p3-sign.douyinpic.com/tos-cn-p-0015/o4ZAqfqFPgxeBD3IBy3iACBNXAwiEdgz0F7Qym~noop.jpeg?lk3s=bfd515bb&x-expires=1770379200&x-signature=HF6O373zrvmcdhxuXTiGXrazVZY%3D&from=3218412987",
    "mobileUrl": "https://p3-sign.douyinpic.com/tos-cn-p-0015/o4ZAqfqFPgxeBD3IBy3iACBNXAwiEdgz0F7Qym~noop.jpeg?lk3s=bfd515bb&x-expires=1770379200&x-signature=HF6O373zrvmcdhxuXTiGXrazVZY%3D&from=3218412987"
  },
  {
    "id": "2390979",
    "title": "快过年了给大家摇一个",
    "timestamp": 1770292641,
    "hot": 7709229,
    "url": "https://p3-sign.douyinpic.com/tos-cn-p-0015c000-ce/occcrCQDTDDeAgtFENchkAIWBJCDfBTgj7IGuf~noop.jpeg?lk3s=bfd515bb&x-expires=1770379200&x-signature=UkAxMuawV%2FJS040ah1ALF9FBK68%3D&from=3218412987",
    "mobileUrl": "https://p3-sign.douyinpic.com/tos-cn-p-0015c000-ce/occcrCQDTDDeAgtFENchkAIWBJCDfBTgj7IGuf~noop.jpeg?lk3s=bfd515bb&x-expires=1770379200&x-signature=UkAxMuawV%2FJS040ah1ALF9FBK68%3D&from=3218412987"
  },
  {
    "id": "2390977",
    "title": "官方回应男子从着火电车连救3人",
    "timestamp": 1770292593,
    "hot": 7701796,
    "url": "https://p26-sign.douyinpic.com/tos-cn-p-0015/owfItFUDhBAFyyYQFQ5KsUAh11vgfp2tDA9IEc~noop.jpeg?lk3s=bfd515bb&x-expires=1770379200&x-signature=y2XL8DNCGzlPUSqmwvCrL86Uvi0%3D&from=3218412987",
    "mobileUrl": "https://p26-sign.douyinpic.com/tos-cn-p-0015/owfItFUDhBAFyyYQFQ5KsUAh11vgfp2tDA9IEc~noop.jpeg?lk3s=bfd515bb&x-expires=1770379200&x-signature=y2XL8DNCGzlPUSqmwvCrL86Uvi0%3D&from=3218412987"
  },
  {
    "id": "2390538",
    "title": "唐宫奇案剧宣闯入ai赛道",
    "timestamp": 1770276440,
    "hot": 7697721,
    "url": "https://p3-sign.douyinpic.com/tos-cn-i-0813/osflJn2BD2De694E4tF6eEA1CAAvIAIe2cAIlA~noop.jpeg?lk3s=bfd515bb&x-expires=1770379200&x-signature=LUp2jwl1iqlomqZUYsNfBUgurX0%3D&from=3218412987",
    "mobileUrl": "https://p3-sign.douyinpic.com/tos-cn-i-0813/osflJn2BD2De694E4tF6eEA1CAAvIAIe2cAIlA~noop.jpeg?lk3s=bfd515bb&x-expires=1770379200&x-signature=LUp2jwl1iqlomqZUYsNfBUgurX0%3D&from=3218412987"
  },
  {
    "id": "2390194",
    "title": "彩虹霉豆腐申请出战",
    "timestamp": 1770260864,
    "hot": 7689567,
    "url": "https://p11-sign.douyinpic.com/tos-cn-i-0629/o8SaQIMhCDOgAkAsiihPYIEzxCDwApJBoA1iw~noop.jpeg?lk3s=bfd515bb&x-expires=1770379200&x-signature=rNGCszTe2NaF9djAf68si6oNysw%3D&from=3218412987",
    "mobileUrl": "https://p11-sign.douyinpic.com/tos-cn-i-0629/o8SaQIMhCDOgAkAsiihPYIEzxCDwApJBoA1iw~noop.jpeg?lk3s=bfd515bb&x-expires=1770379200&x-signature=rNGCszTe2NaF9djAf68si6oNysw%3D&from=3218412987"
  },
  {
    "id": "2390776",
    "title": "奥利给首支人物故事短片",
    "timestamp": 1770284465,
    "hot": 7683145,
    "url": "https://p3-sign.douyinpic.com/tos-cn-p-0015/o8VqNHPLiIKYAIpSvLCPiBv0QEORAI8IwaBqy~noop.jpeg?lk3s=bfd515bb&x-expires=1770379200&x-signature=LLjDdknmXa61VfJo5xcQwm6v%2BIE%3D&from=3218412987",
    "mobileUrl": "https://p3-sign.douyinpic.com/tos-cn-p-0015/o8VqNHPLiIKYAIpSvLCPiBv0QEORAI8IwaBqy~noop.jpeg?lk3s=bfd515bb&x-expires=1770379200&x-signature=LLjDdknmXa61VfJo5xcQwm6v%2BIE%3D&from=3218412987"
  },
  {
    "id": "2390324",
    "title": "猴哥来送新春祝福",
    "timestamp": 1770268364,
    "hot": 7681106,
    "url": "https://p3-sign.douyinpic.com/tos-cn-i-0813c000-ce/oUfTFm7EBbDBuESEiTFf4IAfJOAKQgFqEWAQ5A~noop.jpeg?lk3s=bfd515bb&x-expires=1770379200&x-signature=w04Le52xXRdmuDROBouAGxQJTg8%3D&from=3218412987",
    "mobileUrl": "https://p3-sign.douyinpic.com/tos-cn-i-0813c000-ce/oUfTFm7EBbDBuESEiTFf4IAfJOAKQgFqEWAQ5A~noop.jpeg?lk3s=bfd515bb&x-expires=1770379200&x-signature=w04Le52xXRdmuDROBouAGxQJTg8%3D&from=3218412987"
  },
  {
    "id": "2390625",
    "title": "冯大爷是我的春晚后台人脉",
    "timestamp": 1770279853,
    "hot": 7680569,
    "url": "https://p26-sign.douyinpic.com/tos-cn-p-0015/oICErFgwfAET4xy1CBe0EyBEGiADiAEzkgHIvz~noop.jpeg?lk3s=bfd515bb&x-expires=1770379200&x-signature=Ii7JYMHbXzbybiP3wT92%2FwZImAA%3D&from=3218412987",
    "mobileUrl": "https://p26-sign.douyinpic.com/tos-cn-p-0015/oICErFgwfAET4xy1CBe0EyBEGiADiAEzkgHIvz~noop.jpeg?lk3s=bfd515bb&x-expires=1770379200&x-signature=Ii7JYMHbXzbybiP3wT92%2FwZImAA%3D&from=3218412987"
  },
  {
    "id": "2390573",
    "title": "金铲铲之战福星最强阵容",
    "timestamp": 1770277844,
    "hot": 7674186,
    "url": "https://p26-sign.douyinpic.com/tos-cn-p-0015/owu94gEO2f80LDDbAg1qjggQDfAEFACZBByp4Q~noop.jpeg?lk3s=bfd515bb&x-expires=1770379200&x-signature=O%2Fj7HsqgwnNh7%2BZ%2BY6JtYrD%2F0v4%3D&from=3218412987",
    "mobileUrl": "https://p26-sign.douyinpic.com/tos-cn-p-0015/owu94gEO2f80LDDbAg1qjggQDfAEFACZBByp4Q~noop.jpeg?lk3s=bfd515bb&x-expires=1770379200&x-signature=O%2Fj7HsqgwnNh7%2BZ%2BY6JtYrD%2F0v4%3D&from=3218412987"
  },
  {
    "id": "2390276",
    "title": "奶奶牌限量手工AJ超酷的",
    "timestamp": 1770264684,
    "hot": 7672567,
    "url": "https://p26-sign.douyinpic.com/tos-cn-p-0015c000-ce/o8ukRkPoiMaYA7qkPKC6iBmaaCxKAInEBaBIw~noop.jpeg?lk3s=bfd515bb&x-expires=1770379200&x-signature=uXaUl80gQrNE8GWKhVfbqK0jc5U%3D&from=3218412987",
    "mobileUrl": "https://p26-sign.douyinpic.com/tos-cn-p-0015c000-ce/o8ukRkPoiMaYA7qkPKC6iBmaaCxKAInEBaBIw~noop.jpeg?lk3s=bfd515bb&x-expires=1770379200&x-signature=uXaUl80gQrNE8GWKhVfbqK0jc5U%3D&from=3218412987"
  },
  {
    "id": "2391099",
    "title": "郑雅娴和宋雨琦一起OKOK",
    "timestamp": 1770303983,
    "hot": 7671866,
    "url": "https://p3-sign.douyinpic.com/tos-cn-p-0015c000-ce/ocsEFspIEsLD9BVmwwn4JfE1FAA9CAhfSXjLlE~noop.jpeg?lk3s=bfd515bb&x-expires=1770379200&x-signature=QoLfLaw4oBx8qXNMs736H2qvc6A%3D&from=3218412987",
    "mobileUrl": "https://p3-sign.douyinpic.com/tos-cn-p-0015c000-ce/ocsEFspIEsLD9BVmwwn4JfE1FAA9CAhfSXjLlE~noop.jpeg?lk3s=bfd515bb&x-expires=1770379200&x-signature=QoLfLaw4oBx8qXNMs736H2qvc6A%3D&from=3218412987"
  },
  {
    "id": "2391342",
    "title": "丁程鑫嘎嘣一下就睡那了",
    "timestamp": 1770349325,
    "hot": 7657298,
    "url": "https://p26-sign.douyinpic.com/tos-cn-p-0015c000-ce/ocYea80bMJ4TXLfBdSQeXsgvCDOgFsFgTu7SqA~noop.jpeg?lk3s=bfd515bb&x-expires=1770379200&x-signature=Qgc%2F9Pc5pG3M359lbtXTfAyPqmg%3D&from=3218412987",
    "mobileUrl": "https://p26-sign.douyinpic.com/tos-cn-p-0015c000-ce/ocYea80bMJ4TXLfBdSQeXsgvCDOgFsFgTu7SqA~noop.jpeg?lk3s=bfd515bb&x-expires=1770379200&x-signature=Qgc%2F9Pc5pG3M359lbtXTfAyPqmg%3D&from=3218412987"
  },
  {
    "id": "2390521",
    "title": "吴克群携贵州爱心企业助力菜农",
    "timestamp": 1770275962,
    "hot": 7654930,
    "url": "https://p9-sign.douyinpic.com/tos-cn-i-0813c000-ce/osen6AAnTCJH0QwDE5FEgeDuBBA7u7AIEPf08z~noop.jpeg?lk3s=bfd515bb&x-expires=1770379200&x-signature=pD3nMZqfK351TRTl1ZQPIbXyDas%3D&from=3218412987",
    "mobileUrl": "https://p9-sign.douyinpic.com/tos-cn-i-0813c000-ce/osen6AAnTCJH0QwDE5FEgeDuBBA7u7AIEPf08z~noop.jpeg?lk3s=bfd515bb&x-expires=1770379200&x-signature=pD3nMZqfK351TRTl1ZQPIbXyDas%3D&from=3218412987"
  },
  {
    "id": "2391268",
    "title": "被隐匿的真相开播",
    "timestamp": 1770345918,
    "hot": 7653224,
    "url": "https://p26-sign.douyinpic.com/tos-cn-p-0015c000-ce/oYa0AP7QPh3PMYBIjHPhEMFk0ixAPiCBK2XIq~noop.jpeg?lk3s=bfd515bb&x-expires=1770379200&x-signature=tixDIcFkX%2FAo9ItU9%2Bcjcyiibr4%3D&from=3218412987",
    "mobileUrl": "https://p26-sign.douyinpic.com/tos-cn-p-0015c000-ce/oYa0AP7QPh3PMYBIjHPhEMFk0ixAPiCBK2XIq~noop.jpeg?lk3s=bfd515bb&x-expires=1770379200&x-signature=tixDIcFkX%2FAo9ItU9%2Bcjcyiibr4%3D&from=3218412987"
  },
  {
    "id": "2391013",
    "title": "女儿心如水漫过次元壁",
    "timestamp": 1770294411,
    "hot": 7652642,
    "url": "https://p3-sign.douyinpic.com/tos-cn-p-0015/okIIAlAEeIOAB5TofLAdBLIsAGClerAV7BCAua~noop.jpeg?lk3s=bfd515bb&x-expires=1770379200&x-signature=pzWMvn%2FOcPzGLzIE5pERqLcU1tQ%3D&from=3218412987",
    "mobileUrl": "https://p3-sign.douyinpic.com/tos-cn-p-0015/okIIAlAEeIOAB5TofLAdBLIsAGClerAV7BCAua~noop.jpeg?lk3s=bfd515bb&x-expires=1770379200&x-signature=pzWMvn%2FOcPzGLzIE5pERqLcU1tQ%3D&from=3218412987"
  },
  {
    "id": "2391350",
    "title": "一人一首悟空",
    "timestamp": 1770349697,
    "hot": 7652561,
    "url": "https://p26-sign.douyinpic.com/tos-cn-p-0015c000-ce/okfpFX92AvDh1EkESLF11IyjEerEIwBmCNCoMA~noop.jpeg?lk3s=bfd515bb&x-expires=1770379200&x-signature=NMmW1leygai9tgDtfltyLHQw%2Fr4%3D&from=3218412987",
    "mobileUrl": "https://p26-sign.douyinpic.com/tos-cn-p-0015c000-ce/okfpFX92AvDh1EkESLF11IyjEerEIwBmCNCoMA~noop.jpeg?lk3s=bfd515bb&x-expires=1770379200&x-signature=NMmW1leygai9tgDtfltyLHQw%2Fr4%3D&from=3218412987"
  },
  {
    "id": "2390994",
    "title": "徐艺洋骗黄子韬跳水",
    "timestamp": 1770293788,
    "hot": 7651613,
    "url": "https://p3-sign.douyinpic.com/tos-cn-p-0015/o0BgJTNCR8eEBVF7bTIBZuAavbAfVtfEDOCE7D~noop.jpeg?lk3s=bfd515bb&x-expires=1770379200&x-signature=CeUBWv18jDuj%2BmPVVjVJsoH%2Bno4%3D&from=3218412987",
    "mobileUrl": "https://p3-sign.douyinpic.com/tos-cn-p-0015/o0BgJTNCR8eEBVF7bTIBZuAavbAfVtfEDOCE7D~noop.jpeg?lk3s=bfd515bb&x-expires=1770379200&x-signature=CeUBWv18jDuj%2BmPVVjVJsoH%2Bno4%3D&from=3218412987"
  }
]